Workbook

Sheet READ ME "Project Overview"
A1: Personal Finance Analysis Dashboard (2022–2024) "Read Me"
A2: This workbook provides a multi-year analysis of personal income, expenses, crypto holdings, and earning activities across both traditional and digital income streams. The portfolio uses structured example ledger data and dashboard visuals to evaluate net savings, financial efficiency, and year-over-year performance trends. This portfolio and analysis is based on real personal experiences and transactions, however modified into example data for other use. I created this to help understand where, why and what I was doing with my money during a time I went to college and worked.
A7: Project Objectives
A8: Track active and passive income from multiple sources.
A9: Maintain a detailed expense ledger to monitor spending habits.
A10: Track and value cryptocurrency holdings and earnings over time.
A11: Summarize financial performance using interactive dashboards.
A12: Analyze year-over-year growth, savings rates, and cash flow patterns.
A15: Tools & Methods Used
A16: Area | B16: Details
A17: Software | B17: Microsoft Excel, Transitions into SQL
A18: Visualizations | B18: Pie charts, time-series charts, category summaries, net income dashboards
A19: Data Management | B19: Ledger design, multi-sheet data structure, reference tables
A22: Sheet Overview
A23: Sheet Name | B23: Purpose & Description
A24: 2023–24 Portfolio (Dashboard) | B24: Dashboard summarizing Year 2 financial performance with year-over-year comparison metrics. Measures financial progress, spending adjustments, and gains in overall net worth.
A25: 2022–23 Portfolio (Dashboard) | B25: Dashboard summarizing Year 1 financial performance, including total income vs. expenses, crypto valuations, and expense category breakdowns. Highlights net savings and financial patterns.
A26: Crypto Ledger Wallet | B26: Maintains balances of cryptocurrency holdings across wallets and exchanges. Linked to market pricing to produce net worth and performance summaries.
A27: Expenses | B27: Categorized expense ledger tracking dates, vendors, and amounts spent. Supports spending analysis, budgeting, and savings-rate tracking. "Not Included in PDF"
A28: Work Hours | B28: Tracks hours worked, pay rates, and dates across different job roles. Used to compute annual earned income and compare labor earnings to passive income sources. "Not Included in PDF"
A29: Earning Claims | B29: Transaction-level log of income from online sources (survey platforms, apps, freelancing, etc.). Supports income verification, time-value analysis, and platform comparison.
A30: General Crypto Earnings | B30: Records earnings generated from platforms including staking, mining, and rewards. Used to measure passive income growth and annual crypto revenue.
A31: Earning Claims | B31: Transaction-level log of income from online sources (survey platforms, apps, freelancing, etc.). Supports income verification, time-value analysis, and platform comparison.
A32: Crypto Market Price | B32: Reference price sheet used to track cryptocurrency market values. Enables real-time valuation of crypto holdings and supports return-on-investment calculations across the portfolio.
A35: Key Insights Demonstrated
A36: Ability to design and structure financial tracking systems from raw data.
A37: Strong understanding of personal finance categorization and cost analysis.
A38: Proficiency using Excel for analytical reporting and dashboard visualization.
A39: Demonstrated ability to track and evaluate multi-stream income and investments.
A40: Capability to convert personal finance data into business-quality reporting.
A43: Next Development Phase: SQL Migration (In Progress)
A44: This workbook is being migrated into a structured SQL database to enable:
A45: Automated financial reporting
A46: Query-based expense categorization
A47: Performance dashboards for the web/mobile environment

Sheet 2023-24 Portfolio "Dashboard"
A2: 2023-24 Personal Finance Analysis Dashboard
B4: 4
A5: Bank | B5: Credit | C5: Cash | D5: Total | E5: Owed
A6: 873.95 | B6: 0 | C6: =E7+E8+C8 -> 1957 | D6: =(A6+C6)-B6 -> 2830.95 | E6: 0
E7: 501
A8: Expenses By Month | C8: 520 | D8: Folder | E8: 936
A9: Months | B9: Expenses | C9: Gross Income | D9: Net | E9: Savings
A10: June | B10: =Expenses!$B$301 -> -1741.25 | C10: =SUM(Expenses!$C$301:$E$301) -> 2590.25 | D10: =C10+B10 -> 849 | E10: -
A11: July | B11: =Expenses!$B$302 -> -1727.68 | C11: =SUM(Expenses!$C$302:$E$302) -> 1657 | D11: =C11+B11 -> -70.68 | E11: -
A12: August | B12: =Expenses!$B$303 -> -1866.74 | C12: =SUM(Expenses!$C$303:$E$303) -> 3038.75 | D12: =C12+B12 -> 1172.01 | E12: -
A13: September | B13: =Expenses!$B$304 -> -911.95 | C13: =SUM(Expenses!$C$304:$E$304) -> 2964.25 | D13: =C13+B13 -> 2052.3 | E13: -
A14: October | B14: =Expenses!$B$305 -> -996.32 | C14: =SUM(Expenses!$C$305:$E$305) -> 3298 | D14: =C14+B14 -> 2301.68 | E14: -
A15: November | B15: =Expenses!$B$306 -> -963.7 | C15: =SUM(Expenses!$C$306:$E$306) -> 3322.25 | D15: =C15+B15 -> 2358.55 | E15: -
A16: December | B16: =Expenses!$B$307 -> -1835.44 | C16: =SUM(Expenses!$C$307:$E$307) -> 1526.625 | D16: =C16+B16 -> -308.815 | E16: -
A17: January | B17: =Expenses!$B$308 -> -869.93 | C17: =SUM(Expenses!$C$308:$E$308) -> 2044.5 | D17: =C17+B17 -> 1174.57 | E17: -
A18: February | B18: =Expenses!$B$309 -> -2345.87 | C18: =SUM(Expenses!$C$309:$E$309) -> 1763.875 | D18: =C18+B18 -> -581.995 | E18: -
A19: March | B19: =Expenses!$B$310 -> -1581.39 | C19: =SUM(Expenses!$C$310:$E$310) -> 2869.625 | D19: =C19+B19 -> 1288.235 | E19: -
A20: April | B20: =Expenses!$B$311 -> -1280.14 | C20: =SUM(Expenses!$C$311:$E$311) -> 2336.75 | D20: =C20+B20 -> 1056.61 | E20: -
A21: May | B21: =Expenses!$B$312 -> -1674.68 | C21: =SUM(Expenses!$C$312:$E$312) -> 992.5 | D21: =C21+B21 -> -682.18 | E21: -
A22: Totals | B22: =SUM(B10:B21) -> -17795.09 | C22: =SUM(C10:C21) -> 28404.375 | D22: =SUM(D10:D21) -> 10609.285 | E22: 0
A23: Expenses By Category
A24: Category | B24: June Expenses | C24: July Expenses | D24: Auguest | E24: September | F24: October | G24: November | H24: December | I24: January | J24: February | K24: March | L24: April | M24: May | N24: Total
A25: Flights | B25: =Expenses!C188 -> -227.8 | C25: =Expenses!H188 -> -300 | D25: =Expenses!M188 -> 0 | E25: =Expenses!R188 -> 0 | F25: =Expenses!W188 -> 0 | G25: =Expenses!AB188 -> -69.94 | H25: =Expenses!AG188 -> 0 | I25: =Expenses!AL188 -> 0 | J25: =Expenses!AQ188 -> -14.38 | K25: =Expenses!AV188 -> 0 | L25: =Expenses!BA188 -> 0 | M25: =Expenses!BF188 -> 0 | N25: =SUM(B25:L25) -> -612.12
A26: Gas | B26: =Expenses!C197 -> -116 | C26: =Expenses!H196 -> -144.05 | D26: =Expenses!M196 -> -90.01 | E26: =Expenses!R195 -> -50 | F26: =Expenses!W196 -> -100 | G26: =Expenses!AB196 -> -130 | H26: =Expenses!AG197 -> -90 | I26: =Expenses!AL197 -> -140 | J26: =Expenses!AQ197 -> -92.25 | K26: =Expenses!AV197 -> -145 | L26: =Expenses!BA197 -> -166 | M26: =Expenses!BF197 -> -165 | N26: =SUM(B26:L26) -> -1263.31
A27: Gas Station Food | B27: =Expenses!C215 -> -186.31 | C27: =Expenses!H214 -> -150.24 | D27: =Expenses!M215 -> -97.48 | E27: =Expenses!R212 -> -120.98 | F27: =Expenses!W217 -> -104.15 | G27: =Expenses!AB211 -> -43.29 | H27: =Expenses!AG215 -> -94.48 | I27: =Expenses!AL212 -> -86.07 | J27: =Expenses!AQ210 -> -42.63 | K27: =Expenses!AV216 -> -145.67 | L27: =Expenses!BA215 -> -86.28 | M27: =Expenses!BF218 -> -142.25 | N27: =SUM(B27:L27) -> -1157.58
A28: Reg. Store | B28: =Expenses!C225 -> -296.57 | C28: =Expenses!H221 -> -149.38 | D28: =Expenses!M225 -> -135.11 | E28: =Expenses!R222 -> -138.86 | F28: =Expenses!W229 -> -145.27 | G28: =Expenses!AB221 -> -49.52 | H28: =Expenses!AG226 -> -195.29 | I28: =Expenses!AL219 -> -154.33 | J28: =Expenses!AQ230 -> -517.9 | K28: =Expenses!AV225 -> -28.12 | L28: =Expenses!BA225 -> -114.91 | M28: =Expenses!BF229 -> -186.76 | N28: =SUM(B28:L28) -> -1925.26
A29: Restaurants | B29: =Expenses!C249 -> -608.86 | C29: =Expenses!H243 -> -588.75 | D29: =Expenses!M243 -> -340.93 | E29: =Expenses!R231 -> -88.7 | F29: =Expenses!W244 -> -264.45 | G29: =Expenses!AB238 -> -137.03 | H29: =Expenses!AG234 -> -128.03 | I29: =Expenses!AL232 -> -202.13 | J29: =Expenses!AQ255 -> -447.88 | K29: =Expenses!AV244 -> -346.97 | L29: =Expenses!BA252 -> -642.94 | M29: =Expenses!BF250 -> -534.65 | N29: =SUM(B29:L29) -> -3796.67
A30: Bars | B30: =Expenses!C255 -> -120 | C30: =Expenses!H249 -> -120 | D30: =Expenses!M250 -> -152 | E30: =Expenses!R237 -> -200 | F30: =Expenses!W250 -> 0 | G30: =Expenses!AB244 -> 0 | H30: =Expenses!AG240 -> 0 | I30: =Expenses!AL241 -> -94.35 | J30: =Expenses!AQ279 -> -784.83 | K30: =Expenses!AV273 -> -558.29 | L30: =Expenses!BA270 -> -175.92 | M30: =Expenses!BF267 -> -306.3 | N30: =SUM(B30:L30) -> -2205.39
A31: Activities | B31: =Expenses!C262 -> -124.56 | C31: =Expenses!H256 -> -82.21 | D31: =Expenses!M263 -> -462.81 | E31: =Expenses!R243 -> -32 | F31: =Expenses!W256 -> -40 | G31: =Expenses!AB251 -> -437.95 | H31: =Expenses!AG246 -> -1080 | I31: =Expenses!AL247 -> -35 | J31: =Expenses!AQ289 -> -254.46 | K31: =Expenses!AV284 -> -81.5 | L31: =Expenses!BA277 -> -69 | M31: =Expenses!BF274 -> -85.5 | N31: =SUM(B31:L31) -> -2699.49
A32: Gifts | B32: =Expenses!C268 -> 0 | C32: =Expenses!H262 -> 0 | D32: =Expenses!M269 -> -300 | E32: =Expenses!R249 -> 0 | F32: =Expenses!W262 -> -28.18 | G32: =Expenses!AB257 -> 0 | H32: =Expenses!AG252 -> 0 | I32: =Expenses!AL253 -> 0 | J32: =Expenses!AQ295 -> 0 | K32: =Expenses!AV290 -> 0 | L32: =Expenses!BA283 -> 0 | M32: =Expenses!BF280 -> 0 | N32: =SUM(B32:L32) -> -328.18
A33: Other | B33: =Expenses!C275 -> -61.15 | C33: =Expenses!H271 -> -193.05 | D33: =Expenses!M278 -> -288.4 | E33: =Expenses!R260 -> -281.41 | F33: =Expenses!W273 -> -314.27 | G33: =Expenses!AB267 -> -95.97 | H33: =Expenses!AG262 -> -247.64 | I33: =Expenses!AL264 -> -158.05 | J33: =Expenses!AQ304 -> -191.54 | K33: =Expenses!AV301 -> -275.84 | L33: =Expenses!BA294 -> -25.09 | M33: =Expenses!BF292 -> -254.22 | N33: =SUM(B33:L33) -> -2132.41
A34: School | B34: =Expenses!C281 -> 0 | C34: =Expenses!H277 -> -3315 | D34: =Expenses!M284 -> 0 | E34: =Expenses!R267 -> -69.32 | F34: =Expenses!W279 -> 0 | G34: =Expenses!AB273 -> -1900 | H34: =Expenses!AG268 -> -20.84 | I34: =Expenses!AL270 -> -264.81 | J34: =Expenses!AQ310 -> -19.99 | K34: =Expenses!AV307 -> -126.57 | L34: =Expenses!BA302 -> -176.6 | M34: =Expenses!BF300 -> -114.95 | N34: =SUM(B34:L34) -> -5893.13
A35: Reacuuring Investments | B35: =Expenses!C295 -> -125.05 | C35: =Expenses!H290 -> -114.65 | D35: =Expenses!M298 -> -75.81 | E35: =Expenses!R279 -> -66.17 | F35: =Expenses!W293 -> -68.73 | G35: =Expenses!AB287 -> -110.4 | H35: =Expenses!AG282 -> -126.24 | I35: =Expenses!AL288 -> -95.26 | J35: =Expenses!AQ329 -> -104.98 | K35: =Expenses!AV327 -> -116.1 | L35: =Expenses!BA324 -> -140.83 | M35: =Expenses!BF322 -> -135.1 | N35: =SUM(B35:L35) -> -1144.22
A36: Total Expenses (All) | B36: =SUM(B25:B35) -> -1866.3 | C36: =SUM(C25:C35) -> -5157.33 | D36: =SUM(D25:D35) -> -1942.55 | E36: =SUM(E25:E35) -> -1047.44 | F36: =SUM(F25:F35) -> -1065.05 | G36: =SUM(G25:G35) -> -2974.1 | H36: =SUM(H25:H35) -> -1982.52 | I36: =SUM(I25:I35) -> -1230 | ... N36: =SUM(N25:N35) -> -23157.76
A37: Crypto Asset Totals and Earnings
A38: Crypto Exchanges | B38: ='Crypto Ledger Wallet'!D16 -> 934.98906 | C38: NFT Asset Total (Future Return)
A39: Crypto Wallets | B39: ='Crypto Ledger Wallet'!D37 -> 295.56259 | C39: ='Crypto Ledger Wallet'!I104 -> 3852.0723
A40: Crypto Staking | B40: ='Crypto Ledger Wallet'!D47 -> 29.531828 | C40: Passive Earnings (AVG./Day)
A41: Crypto App Miners | B41: ='Crypto Ledger Wallet'!I61 -> 966.95465 | C41: {=Table34[Total Passive Earnings ($/Day)]} -> 3.7860646
A42: GPU/CPU & Data Miners | B42: ='Crypto Ledger Wallet'!D60 -> 223.22833 | C42: Passive Earnings (AVG./Week)
A43: NFT Accounts | B43: ='Crypto Ledger Wallet'!D75 -> 68.120764 | C43: {=Table34[Total Passive Earnings ($/Week)]} -> 25.869213
A44: Investment Apps | B44: ='Crypto Ledger Wallet'!I8 -> 220.46 | C44: Passive Earnings (AVG./Week)
A45: Crypto Faucets/Surveys | B45: ='Crypto Ledger Wallet'!I24 -> 188.72859 | C45: {=Table34[Total Passive Earnings ($/Month)]} -> 111.15452
A46: Paid Tasks/Survey Apps | B46: ='Crypto Ledger Wallet'!I35 -> 41.605 | C46: Passive Earnings (AVG./Year)
A47: Receipts | B47: ='Crypto Ledger Wallet'!I47 -> 181.69794 | C47: {=Table34[Total Passive Earnings ($/Year)]} -> 1328.7551
A48: App Miners | B48: ='Crypto Ledger Wallet'!I61 -> 966.95465 | C48: Estimated Earning Claims
A49: Driving & Fitness Apps | B49: ='Crypto Ledger Wallet'!I77 -> 131.22816 | C49: ='Crypto Claims'!F86 -> 217.99589
A50: Total: | B50: =SUM(B38:B49) -> 4249.0616
A52: Total Wealth: Assets
A53: =B50+C39 -> 8101.1339

Sheet 2022-23 Portfolio "Dashboard"
A2: 2022-23 Personal Finance Analysis Dashboard
A5: Bank | B5: Credit | C5: Cash | D5: Total | E5: Owed
A6: 1185.12 | B6: 0 | C6: 256 | D6: =('2022-23 Portfolio "Dashboard"'!$A6+'2022-23 Portfolio "Dashboard"'!$C6)-'2022-23 Portfolio "Dashboard"'!$B6 -> 1441.12 | E6: 45
A8: Expenses By Month
A9: Months | B9: Expenses | C9: Gross Income | D9: Net | E9: Savings
A10: June | B10: =Expenses!$A$157 -> -995.4 | C10: =SUM(Expenses!$B$157:$D$157) -> 1943.45 | D10: ='2022-23 Portfolio "Dashboard"'!$C10+('2022-23 Portfolio "Dashboard"'!$B10) -> 948.05 | E10: -
A11: July | B11: =Expenses!$A$160 -> -1233.7 | C11: =SUM(Expenses!$B$160:$D$160) -> 2782.5 | D11: ='2022-23 Portfolio "Dashboard"'!$C11+('2022-23 Portfolio "Dashboard"'!$B11) -> 1548.8 | E11: -
A12: August | B12: =Expenses!$A$163 -> -881.65 | C12: =SUM(Expenses!$B$163:$D$163) -> 2579.25 | D12: ='2022-23 Portfolio "Dashboard"'!$C12+('2022-23 Portfolio "Dashboard"'!$B12) -> 1697.6 | E12: -
A13: September | B13: =Expenses!$A$166 -> -1516.86 | C13: =SUM(Expenses!$B$166:$D$166) -> 3384 | D13: ='2022-23 Portfolio "Dashboard"'!$C13+('2022-23 Portfolio "Dashboard"'!$B13) -> 1867.14 | E13: -
A14: October | B14: =Expenses!$A$169 -> -1375.68 | C14: =SUM(Expenses!$B$169:$D$169) -> 1130 | D14: ='2022-23 Portfolio "Dashboard"'!$C14+('2022-23 Portfolio "Dashboard"'!$B14) -> -245.68 | E14: -
A15: November | B15: =Expenses!$A$172 -> -1206.44 | C15: =SUM(Expenses!$B$172:$D$172) -> 1189.5 | D15: ='2022-23 Portfolio "Dashboard"'!$C15+('2022-23 Portfolio "Dashboard"'!$B15) -> -16.94 | E15: -
A16: December | B16: =Expenses!$F$157 -> -2427.13 | C16: =SUM(Expenses!$G$157:$I$157) -> 1127 | D16: ='2022-23 Portfolio "Dashboard"'!$C16+('2022-23 Portfolio "Dashboard"'!$B16) -> -1300.13 | E16: -
A17: January | B17: =Expenses!$F$160 -> -2015.38 | C17: =SUM(Expenses!$G$160:$I$160) -> 390 | D17: ='2022-23 Portfolio "Dashboard"'!$C17+('2022-23 Portfolio "Dashboard"'!$B17) -> -1625.38 | E17: -
A18: February | B18: =Expenses!$F$163 -> -1031.88 | C18: =SUM(Expenses!$G$163:$I$163) -> 1041 | D18: ='2022-23 Portfolio "Dashboard"'!$C18+('2022-23 Portfolio "Dashboard"'!$B18) -> 9.12 | E18: -
A19: March | B19: =Expenses!$F$166 -> -1984.81 | C19: =SUM(Expenses!$G$166:$I$166) -> 1020 | D19: ='2022-23 Portfolio "Dashboard"'!$C19+('2022-23 Portfolio "Dashboard"'!$B19) -> -964.81 | E19: -
A20: April | B20: =Expenses!$F$169 -> -669.2 | C20: =SUM(Expenses!$G$169:$I$169) -> 1840.5 | D20: ='2022-23 Portfolio "Dashboard"'!$C20+('2022-23 Portfolio "Dashboard"'!$B20) -> 1171.3 | E20: -
A21: May | B21: =Expenses!$F$172 -> -1211.14 | C21: =SUM(Expenses!$G$172:$I$172) -> 2515.5 | D21: ='2022-23 Portfolio "Dashboard"'!$C21+('2022-23 Portfolio "Dashboard"'!$B21) -> 1304.36 | E21: -
A22: Totals | B22: =SUM('2022-23 Portfolio "Dashboard"'!$B$10:$B$21) -> -16549.27 | C22: =SUM('2022-23 Portfolio "Dashboard"'!$C$10:$C$21) -> 20942.7 | D22: =SUM('2022-23 Portfolio "Dashboard"'!$D$10:$D$21) -> 4393.43 | E22: 0
A23: Expenses By Category
A24: Category | B24: June Expenses | C24: July Expenses | D24: Auguest | E24: September | F24: October | G24: November | H24: December | I24: January | J24: February | K24: March | L24: April | M24: May | N24: Total
A25: Flights | B25: =Expenses!C26 -> 0 | C25: =Expenses!H16 -> 0 | D25: =Expenses!M16 -> 0 | E25: =Expenses!R16 -> -376.2 | F25: =Expenses!W16 -> 0 | G25: =Expenses!AB16 -> -386.2 | H25: =Expenses!AG16 -> 0 | I25: =Expenses!AL16 -> 0 | J25: =Expenses!AQ16 -> 0 | K25: =Expenses!AV16 -> 0 | L25: =Expenses!BA16 -> 0 | M25: =Expenses!BF16 -> 0 | N25: =SUM(B25:M25) -> -762.4
A26: Gas | B26: =Expenses!C35 -> -105.3 | C26: =Expenses!H25 -> -95.3 | D26: =Expenses!M26 -> -113.75 | E26: =Expenses!R25 -> -110.01 | F26: =Expenses!W23 -> -115 | G26: =Expenses!AB25 -> -110.05 | H26: =Expenses!AG26 -> -145.06 | I26: =Expenses!AL25 -> -137.13 | J26: =Expenses!AQ26 -> -175.25 | K26: =Expenses!AV27 -> -165.27 | L26: =Expenses!BA23 -> -66.05 | M26: =Expenses!BF25 -> -120.01 | N26: =SUM(B26:M26) -> -1458.18
A27: Gas Station Food | B27: =Expenses!C62 -> -131.18 | C27: =Expenses!H56 -> -211.29 | D27: =Expenses!M41 -> -85.89 | E27: =Expenses!R47 -> -117.32 | F27: =Expenses!W51 -> -168.24 | G27: =Expenses!AB46 -> -97.81 | H27: =Expenses!AG42 -> -106.17 | I27: =Expenses!AL39 -> -128.69 | J27: =Expenses!AQ40 -> -72.41 | K27: =Expenses!AV44 -> -103.99 | L27: =Expenses!BA36 -> -66.64 | M27: =Expenses!BF40 -> -92.62 | N27: =SUM(B27:M27) -> -1382.25
A28: Reg. Store | B28: =Expenses!C71 -> -61.62 | C28: =Expenses!H63 -> -48.79 | D28: =Expenses!M51 -> -98.25 | E28: =Expenses!R58 -> -122.39 | F28: =Expenses!W59 -> -78.44 | G28: =Expenses!AB53 -> -55.22 | H28: =Expenses!AG49 -> -98.6 | I28: =Expenses!AL50 -> -172.11 | J28: =Expenses!AQ51 -> -117.55 | K28: =Expenses!AV58 -> -436.75 | L28: =Expenses!BA49 -> -184.71 | M28: =Expenses!BF49 -> -214.22 | N28: =SUM(B28:M28) -> -1688.65
A29: Restaurants | B29: =Expenses!C95 -> -284.82 | C29: =Expenses!H85 -> -195.72 | D29: =Expenses!M68 -> -270.12 | E29: =Expenses!R82 -> -239.69 | F29: =Expenses!W93 -> -557.12 | G29: =Expenses!AB71 -> -153.81 | H29: =Expenses!AG73 -> -681.87 | I29: =Expenses!AL70 -> -455.26 | J29: =Expenses!AQ70 -> -279.96 | K29: =Expenses!AV89 -> -742.96 | L29: =Expenses!BA59 -> -85.06 | M29: =Expenses!BF71 -> -466.16 | N29: =SUM(B29:M29) -> -4412.55
A30: Bars | B30: =Expenses!C111 -> -173 | C30: =Expenses!H99 -> -191 | D30: =Expenses!M79 -> -112.64 | E30: =Expenses!R97 -> -201.46 | F30: =Expenses!W105 -> -110 | G30: =Expenses!AB81 -> -80 | H30: =Expenses!AG80 -> -100 | I30: =Expenses!AL80 -> -150 | J30: =Expenses!AQ80 -> -95 | K30: =Expenses!AV96 -> -120 | L30: =Expenses!BA67 -> -160 | M30: =Expenses!BF78 -> -120 | N30: =SUM(B30:M30) -> -1613.1
A31: Activities | B31: =Expenses!C117 -> -6.25 | C31: =Expenses!H109 -> -298.78 | D31: =Expenses!M85 -> 0 | E31: =Expenses!R103 -> -27 | F31: =Expenses!W110 -> -48.38 | G31: =Expenses!AB86 -> -10 | H31: =Expenses!AG88 -> -123 | I31: =Expenses!AL86 -> -56.95 | J31: =Expenses!AQ85 -> -24 | K31: =Expenses!AV107 -> -118.4 | L31: =Expenses!BA74 -> -51.94 | M31: =Expenses!BF86 -> -66.5 | N31: =SUM(B31:M31) -> -831.2
A32: Gifts | B32: =Expenses!C123 -> -19.99 | C32: =Expenses!H115 -> 50 | D32: =Expenses!M91 -> 0 | E32: =Expenses!R109 -> -62.33 | F32: =Expenses!W115 -> -23.04 | G32: =Expenses!AB92 -> 0 | H32: =Expenses!AG113 -> -896.75 | I32: =Expenses!AL92 -> -529.37 | J32: =Expenses!AQ94 -> -18.6 | K32: =Expenses!AV112 -> -58.38 | L32: =Expenses!BA80 -> 0 | M32: =Expenses!BF92 -> -100 | N32: =SUM(B32:M32) -> -1658.46
A33: Other | B33: =Expenses!C132 -> -213.24 | C33: =Expenses!H125 -> -242.82 | D33: =Expenses!M101 -> -201 | E33: =Expenses!R119 -> -260.46 | F33: =Expenses!W125 -> -275.46 | G33: =Expenses!AB102 -> -313.35 | H33: =Expenses!AG122 -> -275.68 | I33: =Expenses!AL104 -> -385.87 | J33: =Expenses!AQ103 -> -148.71 | K33: =Expenses!AV125 -> -239.06 | L33: =Expenses!BA87 -> -54.8 | M33: =Expenses!BF98 -> -31.63 | N33: =SUM(B33:M33) -> -2642.08
A34: School | B34: =Expenses!C138 -> 0 | C34: =Expenses!H131 -> 0 | D34: =Expenses!M107 -> 0 | E34: =Expenses!R125 -> 0 | F34: =Expenses!W131 -> -960 | G34: =Expenses!AB108 -> 0 | H34: =Expenses!AG128 -> 0 | I34: =Expenses!AL110 -> 0 | J34: =Expenses!AQ109 -> -2166 | K34: =Expenses!AV131 -> 0 | L34: =Expenses!BA88 -> 0 | M34: =Expenses!BF104 -> 0 | N34: =SUM(B34:M34) -> -3126
A35: Reacuuring Investments | B35: =Expenses!C152 -> -66 | C35: =Expenses!H146 -> -132.7 | D35: =Expenses!M123 -> -130.95 | E35: =Expenses!R141 -> -137.95 | F35: =Expenses!W146 -> -101.94 | G35: =Expenses!AB124 -> -105.95 | H35: =Expenses!AG145 -> -125.94 | I35: =Expenses!AL129 -> -176 | J35: =Expenses!AQ132 -> -155.02 | K35: =Expenses!AV158 -> -237.14 | L35: =Expenses!BA114 -> -147.17 | M35: =Expenses!BF121 -> -98.04 | N35: =SUM(B35:M35) -> -1614.8
A36: Total Expenses (All) | B36: =SUM(B25:B35) -> -1061.4 | C36: =SUM(C25:C35) -> -1366.4 | D36: =SUM(D25:D35) -> -1012.6 | E36: =SUM(E25:E35) -> -1654.81 | F36: =SUM(F25:F35) -> -2437.62 | G36: =SUM(G25:G35) -> -1312.39 | H36: =SUM(H25:H35) -> -2553.07 | I36: =SUM(I25:I35) -> -2191.38 | ... N36: =SUM(N25:N35) -> -21189.67
A37: Crypto Asset Totals and Earnings
A38: Crypto Exchanges | B38: ='Crypto Ledger Wallet'!D16 -> 934.98906 | C38: NFT Asset Total (Future Return)
A39: Crypto Wallets | B39: ='Crypto Ledger Wallet'!D37 -> 295.56259 | C39: ='Crypto Ledger Wallet'!I104 -> 3852.0723
A40: Crypto Staking | B40: ='Crypto Ledger Wallet'!D47 -> 29.531828 | C40: Passive Earnings (AVG./Day)
A41: Crypto App Miners | B41: ='Crypto Ledger Wallet'!I61 -> 966.95465 | C41: {=Table34[Total Passive Earnings ($/Day)]} -> 3.7860646
A42: GPU/CPU & Data Miners | B42: ='Crypto Ledger Wallet'!D60 -> 223.22833 | C42: Passive Earnings (AVG./Week)
A43: NFT Accounts | B43: ='Crypto Ledger Wallet'!D75 -> 68.120764 | C43: {=Table34[Total Passive Earnings ($/Week)]} -> 25.869213
A44: Investment Apps | B44: ='Crypto Ledger Wallet'!I8 -> 220.46 | C44: Passive Earnings (AVG./Week)
A45: Crypto Faucets/Surveys | B45: ='Crypto Ledger Wallet'!I24 -> 188.72859 | C45: {=Table34[Total Passive Earnings ($/Month)]} -> 111.15452
A46: Paid Tasks/Survey Apps | B46: ='Crypto Ledger Wallet'!I35 -> 41.605 | C46: Passive Earnings (AVG./Year)
A47: Receipts | B47: ='Crypto Ledger Wallet'!I47 -> 181.69794 | C47: {=Table34[Total Passive Earnings ($/Year)]} -> 1328.7551
A48: App Miners | B48: ='Crypto Ledger Wallet'!I61 -> 966.95465 | C48: Estimated Earning Claims
A49: Driving & Fitness Apps | B49: ='Crypto Ledger Wallet'!I77 -> 131.22816 | C49: ='Crypto Claims'!F86 -> 217.99589
A50: Total: | B50: =SUM(B38:B49) -> 4249.0616
A52: Total Wealth: Assets
A53: =B50+C39 -> 8101.1339

Sheet Crypto Ledger Wallet
A1: Fincancial Portfolio: Investment Ledger
A2: Crypto Ledger Wallet
D3: Start Date: (9/27/21)
A4: Crypto Exchanges | D4: Current: 12/26/23 | F4: Investment Apps | I4: Current: 12/26/23
A5: Accounts: Crypto Exchanges | B5: Coin | C5: Amount (Coin) | D5: Amount ($) | F5: Accounts: Invest. Apps | G5: Coin | H5: Amount (Coin) | I5: Amount ($)
A6: Coinbase | F6: Acorns | G6: Dollars | H6: 217.99 | I6: ='Crypto Ledger Wallet'!$H6 -> 217.99
A7: Asset 1 | B7: SOL | C7: 5.01048 | D7: ='Crypto Ledger Wallet'!$C7*'Crypto Market Price Data'!$C$9 -> 620.69826 | F7: Stash | G7: BTC | H7: 2.47 | I7: ='Crypto Ledger Wallet'!$H7 -> 2.47
A8: Asset 2 | B8: GALA | C8: 26342.98 | D8: ='Crypto Ledger Wallet'!$C8*'Crypto Market Price Data'!$C$21 -> 176.83753 | H8: Total: | I8: =SUM('Crypto Ledger Wallet'!$I$6:$I$7) -> 220.46
A9: Binance US | B9: BNB | C9: 0.05605841 | D9: ='Crypto Ledger Wallet'!$C9*'Crypto Market Price Data'!$C$7 -> 45.671908
A10: Huobi Global | B10: BTC | C10: 0 | D10: ='Crypto Ledger Wallet'!$C10*'Crypto Market Price Data'!$C$5 -> 0 | F10: Paid Videos | I10: Current: 12/26/23
A11: Uphold | B11: BAT | C11: 153.486 | D11: ='Crypto Ledger Wallet'!$C11*'Crypto Market Price Data'!$C$13 -> 38.275878 | F11: Accounts: Paid Videos | G11: Coin | H11: Amount (Coin) | I11: Amount ($)
A12: Kucoin | B12: SOUL | C12: 0 | D12: ='Crypto Ledger Wallet'!$C12*'Crypto Market Price Data'!$C$23 -> 0 | F12: HideOutTV | G12: Points | H12: 162.9 | I12: =H12*0.0005 -> 0.08145
A13: Stormgain | B13: BTC | C13: 0.0003 | D13: ='Crypto Ledger Wallet'!$C13*'Crypto Market Price Data'!$C$5 -> 25.4985 | F13: LootTV | G13: Points | H13: 262.6 | I13: =H13*0.0005 -> 0.1313
A14: Crypto.com | B14: CRO | C14: 280.21 | D14: ='Crypto Ledger Wallet'!$C14*'Crypto Market Price Data'!$C$12 -> 28.006989 | H14: Total: | I14: =SUM('Crypto Ledger Wallet'!$I$12:$I$13) -> 0.21275
A15: Uniswap | B15: BTC | C15: 0 | D15: ='Crypto Ledger Wallet'!$C15*'Crypto Market Price Data'!$C$5 -> 0
C16: Total: | D16: =SUM('Crypto Ledger Wallet'!$D$6:$D$15) -> 934.98906 | F16: Faucets/Surveys | I16: Current: 12/26/23
F17: Accounts: Faucets/Surveys | G17: Coin | H17: Amount (Coin) | I17: Amount ($)
A18: Crypto Wallets | D18: Current: 12/26/23 | F18: Cointiply
A19: Accounts: Crypto Wallets | B19: Coin | C19: Amount (Coin) | D19: Amount ($) | F19: - Account 1 (Dan) | G19: BTC | H19: 0.00112252 | I19: ='Crypto Ledger Wallet'!$H19*'Crypto Market Price Data'!$C$5 -> 95.408587
A20: Coinbase Wallet | F20: - Account 2 (Zach) | G20: BTC | H20: 0 | I20: ='Crypto Ledger Wallet'!$H20*'Crypto Market Price Data'!$C$5 -> 0
A21: Asset 1 | B21: ETH | C21: 0.001 | D21: ='Crypto Ledger Wallet'!$C21*'Crypto Market Price Data'!$C$6 -> 2.74059 | F21: Inboxdollars | G21: Dollars | H21: 6.13 | I21: ='Crypto Ledger Wallet'!$H21 -> 6.13
A22: Metamask | F22: Swagbucks | G22: Points | H22: 4081 | I22: ='Crypto Ledger Wallet'!$H22/100 -> 40.81
A23: Etherium Network | F23: PaidViewpoint | G23: Dollars | H23: 46.38 | I23: ='Crypto Ledger Wallet'!$H23 -> 46.38
A24: - Asset 1: Main Account | B24: ETH | C24: 0.0003 | D24: ='Crypto Ledger Wallet'!$C24*'Crypto Market Price Data'!$C$6 -> 0.822177 | I24: =SUM('Crypto Ledger Wallet'!$I$18:$I$23) -> 188.72859
A25: - Asset 2: NFT Accounts | B25: ETH | C25: 0 | D25: ='Crypto Ledger Wallet'!$C25*'Crypto Market Price Data'!$C$6 -> 0
A26: - Asset 3: JumpTask | B26: BNB | C26: 0.0191 | D26: ='Crypto Ledger Wallet'!$C26*'Crypto Market Price Data'!$C$7 -> 15.561152 | F26: Paid Tasks/Surveys Apps | I26: Current: 12/26/23
A27: - Asset 4: Cops & Robber's | B27: ETH | C27: 0.004 | D27: ='Crypto Ledger Wallet'!$C27*'Crypto Market Price Data'!$C$6 -> 10.96236 | F27: Accounts: Paid Tasks/Survey Apps | G27: Coin | H27: Amount (Coin) | I27: Amount ($)
A28: - Asset 5: League of Kingdoms | B28: ETH | C28: 0.005798 | D28: ='Crypto Ledger Wallet'!$C28*'Crypto Market Price Data'!$C$6 -> 15.889941 | F28: Rewards App | G28: Points | H28: 31542 | I28: =(H28/30000)*25 -> 26.285
A29: - Asset 6: The Sandbox | B29: ETH | C29: 0 | D29: ='Crypto Ledger Wallet'!$C29*'Crypto Market Price Data'!$C$6 -> 0 | F29: Google Rewards | G29: Dollars | H29: 0.35 | I29: =H29 -> 0.35
A30: - Asset 7: Gala Games | B30: ETH | C30: 0.002691 | D30: ='Crypto Ledger Wallet'!$C30*'Crypto Market Price Data'!$C$6 -> 7.3749277 | F30: Surveys App | G30: Dollars | H30: 12.1 | I30: =H30 -> 12.1
A31: Ronin | F31: Poll Pay | G31: Dollars | H31: 2.87 | I31: =H31 -> 2.87
A32: Asset 1 | B32: AXS | C32: ='Crypto Claims'!B86 -> 243.3782 | D32: ='Crypto Ledger Wallet'!$C32*'Crypto Market Price Data'!$C$19 -> 242.21144 | F32: Qmee | G32: Dollars | H32: 0 | I32: =H32 -> 0
A33: Electronium | B33: ETH | C33: 0 | D33: ='Crypto Ledger Wallet'!$C33*'Crypto Market Price Data'!$C$6 -> 0 | F33: Influnce | G33: Dollars | H33: 0 | I33: =H33 -> 0
A34: Ecto Wallet | B34: SOUL | C34: 0 | D34: ='Crypto Ledger Wallet'!$C34*'Crypto Market Price Data'!$C$23 -> 0 | F34: Slicethepie | G34: Dollars | H34: 0 | I34: =H34 -> 0
A35: Helium | B35: HNT | C35: 0 | D35: ='Crypto Ledger Wallet'!$C35 -> 0 | H35: Total: | I35: =SUM(I28:I34) -> 41.605
A36: Juicy Field | B36: BTC | C36: 0 | D36: ='Crypto Ledger Wallet'!$C36*'Crypto Market Price Data'!$C$5 -> 0
C37: Total: | D37: =SUM('Crypto Ledger Wallet'!$D$20:$D$36) -> 295.56259 | F37: Receipt Apps | I37: Current: 12/26/23
F38: Accounts: Receipt Apps | G38: Coin | H38: Amount (Coin) | I38: Amount ($)
A39: Staking Wallets | D39: Current: 12/26/23 | F39: Receipt Hog | G39: Points | H39: 3982 | I39: =(H39/6500)*40 -> 24.504615
A40: Accounts: Staking Wallets | B40: Coin | C40: Amount (Coin) | D40: Amount ($) | F40: Receipt Pal | G40: Points | H40: 13965 | I40: =(H40/32250)*100 -> 43.302326
A41: BlockFi | B41: BTC | C41: 0 | D41: ='Crypto Ledger Wallet'!$C41*'Crypto Market Price Data'!$C$5 -> 0 | F41: Fetch Rewards | G41: Points | H41: 36729 | I41: =(H41/52500)*50 -> 34.98
A42: Yoroi Cardano Wallet | B42: ADA | C42: 0 | D42: ='Crypto Ledger Wallet'!$C42*'Crypto Market Price Data'!$C$8 -> 0 | F42: Coinout | G42: Dollars | H42: 32410 | I42: =H42/1000 -> 32.41
A43: Attomic Wallet | B43: ADA | C43: 0 | D43: ='Crypto Ledger Wallet'!$C43*'Crypto Market Price Data'!$C$8 -> 0 | F43: Receipt Jar | G43: Points | H43: 3749 | I43: =(H43/1000)*5 -> 18.745
A44: Exodus Wallet | B44: ADA | C44: 0 | D44: ='Crypto Ledger Wallet'!$C44*'Crypto Market Price Data'!$C$8 -> 0 | F44: Pogo | G44: Points | H44: 7736 | I44: =(H44/1000)*1 -> 7.736
A45: Ronin Staking | B45: AXS | C45: 24.65 | D45: ='Crypto Ledger Wallet'!$C45*'Crypto Market Price Data'!C19 -> 24.531828 | F45: Ibotta | G45: Dollars | H45: 14.3 | I45: =H45 -> 14.3
A46: ThunderCore | B46: TT | C46: 5 | D46: ='Crypto Ledger Wallet'!$C46 -> 5 | F46: Tada | G46: Dollars | H46: 5.72 | I46: =H46 -> 5.72
C47: Total: | D47: =SUM('Crypto Ledger Wallet'!$D$41:$D$46) -> 29.531828 | H47: Total: | I47: =SUM('Crypto Ledger Wallet'!$I$39:$I$46) -> 181.69794
A49: GPU/CPU & Data Miners | D49: Current: 12/26/23 | F49: App Miners | I49: Current: 12/26/23
A50: Accounts: GPU/CPU & Data Miners | B50: Coin | C50: Amount (Coin) | D50: Amount ($) | F50: Accounts: Crypto App Miners | G50: Coin | H50: Amount (Coin) | I50: Amount ($)
A51: HoneyGain | F51: Pi Wallet | G51: Pi Network | H51: 19138 | I51: 0
A52: Asset 1: Jumptask | B52: JMPT | C52: 34 | D52: ='Crypto Ledger Wallet'!$C52*'Crypto Market Price Data'!$C$34 -> 25.338092 | F52: Bee Wallet | G52: Bee Network | H52: 7501 | I52: 0
A53: Unmineable | F53: Sperax Wallet | G53: SPX | H53: 1522.67 | I53: ='Crypto Ledger Wallet'!$H53*'Crypto Market Price Data'!$C$31 -> 917.15439
A54: Asset 1 | B54: ADA | C54: 0 | D54: ='Crypto Ledger Wallet'!$C54*'Crypto Market Price Data'!$C$8 -> 0 | F54: Hi Wallet | G54: HI | H54: 108.5 | I54: ='Crypto Ledger Wallet'!$H54*0.05 -> 5.425
A55: Kryptex | F55: Geo Coin | G55: XYO | H55: 69945.36 | I55: =(('Crypto Ledger Wallet'!$H55/1000)*133.6)*'Crypto Market Price Data'!$C$30 -> 44.366393
A56: Asset 1 | B56: BTC | C56: 0.0022515 | D56: ='Crypto Ledger Wallet'!$C56*'Crypto Market Price Data'!$C$5 -> 191.36624 | F56: Eagle Network | G56: EAN | H56: 300.2034 | I56: 0
A57: IPRoyal Pawns | F57: Star Network | G57: STAR | H57: 2301 | I57: 0
A58: Asset 1 | B58: Dollars | C58: 6.294 | D58: ='Crypto Ledger Wallet'!$C58 -> 6.294 | F58: Bondex Origin | G58: BNDX | H58: 84.48 | I58: ='Crypto Ledger Wallet'!$H58*'Crypto Market Price Data'!$C$33 -> 0.0088704
A59: PacketStream | B59: Dollars | C59: 0.23 | D59: ='Crypto Ledger Wallet'!$C59 -> 0.23 | F59: Midoin | G59: M | H59: 0.00365196 | I59: 0
C60: Total: | D60: =SUM('Crypto Ledger Wallet'!$D$51:$D$59) -> 223.22833 | F60: Geo Cash | G60: GEO | H60: 1.29 | I60: 0
H61: Total: | I61: =SUM('Crypto Ledger Wallet'!$I$51:$I$60) -> 966.95465
A62: NFT Accounts | C62: Start Date: 10/12/21 | D62: 45286
A63: Accounts: NFT Accounts | B63: Coin | C63: Amount (Coin) | D63: Amount ($) | F63: Fitness & Driving Apps | I63: Current: 12/26/23
A64: Gala Games | F64: Accounts: Fitness & Driving Apps | G64: Coin | H64: Amount (Coin) | I64: Amount ($)
A65: Asset 1 | B65: GALA | C65: 5183.167 | D65: ='Crypto Ledger Wallet'!$C65*'Crypto Market Price Data'!$C$21 -> 34.79403 | F65: OnMyWay Driving | G65: Dollars | H65: 8.83 | I65: =H65 -> 8.83
A66: Asset 2 | B66: TOWN | C66: 2855.3 | D66: ='Crypto Ledger Wallet'!$C66*'Crypto Market Price Data'!$C$24 -> 3.3375602 | F66: Safe 2 Save | G66: Points | H66: 12207 | I66: =H66*0.0001 -> 1.2207
A67: Asset 3 | B67: Test Silk | C67: 14.365 | D67: 0 | F67: Miles | G67: Miles | H67: 37453 | I67: =(H67/25000)*5 -> 7.4906
A68: Asset 4 | B68: ETH | C68: 0.00269084 | D68: ='Crypto Ledger Wallet'!$C68*'Crypto Market Price Data'!$C$6 -> 7.3744892 | F68: Paidtogo | G68: Points | H68: 1669.68 | I68: =H68*0.05 -> 83.484
A69: League of Kingdoms | F69: sMiles | G69: Sats | H69: 4.68e-06 | I69: =H69*'Crypto Market Price Data'!$C$5 -> 0.3977766
A70: Asset 1 | B70: DAI | C70: 11.1465 | D70: ='Crypto Ledger Wallet'!$C70*'Crypto Market Price Data'!$C$11 -> 11.140581 | F70: Upside | G70: Dollars | H70: 2.4 | I70: =H70 -> 2.4
A71: Asset 2 | B71: LOKA | C71: 108.41 | D71: ='Crypto Ledger Wallet'!$C71*'Crypto Market Price Data'!$C$22 -> 6.0741039 | F71: Noodle Cash | G71: NODL | H71: 14.00318 | I71: =H71*'Crypto Market Price Data'!$C$33 -> 0.0014703339
A72: Atlas Earth | B72: Dollars | C72: 5.4 | D72: ='Crypto Ledger Wallet'!$C72 -> 5.4 | F72: Million Steps | G72: Steps | H72: 296623 | I72: =H72/100000 -> 2.96623
A73: Blankos | F73: LifeCoin | G73: Points | H73: 300 | I73: =(H73/2500)*50 -> 6
A74: Asset 1 | B74: MOOLA | F74: Walk & Earn | G74: Dollars | H74: 0.63 | I74: =H74 -> 0.63
C75: Total: | D75: =SUM('Crypto Ledger Wallet'!$D$64:$D$74) -> 68.120764 | F75: Cashwalk | G75: Points | H75: 200 | I75: =(H75/10000)*25 -> 0.5
F76: SweatCoin | G76: Points | H76: 11062 | I76: =H76*'Crypto Market Price Data'!C35 -> 17.307384
H77: Total: | I77: =SUM(I65:I76) -> 131.22816
A78: NFT Assets | F78: Estimate at price of purchase | G78: Current: 12/26/23
A79: NFT Asset Account | B79: Asset | C79: Date Purchased | D79: Coin | E79: Gas Fee | F79: Total Price Spent ($) | G79: Future Amount (Coin) | H79: Future Amount ($) | I79: Actual Future Return
A80: Axie Infinity
A81: Asset 1 | B81: x3 Axie: | C81: 44037 | D81: ETH | E81: 3 | F81: 75 | G81: 0.2 | H81: ='Crypto Ledger Wallet'!$G81*'Crypto Market Price Data'!$C$6 -> 548.118 | I81: TRADED
A82: Asset 2 | B82: x1 Axie for Lunachian: Snack Box | C82: Traded | D82: ETH | E82: 0 | F82: Traded for Lunacian Item | G82: 0.002 | H82: ='Crypto Ledger Wallet'!$G82*'Crypto Market Price Data'!$C$6 -> 5.48118 | I82: ='Crypto Ledger Wallet'!$H82 -> 5.48118
A83: Asset 3 | B83: x1 Axie for Lunachian: Firecrackers | C83: Traded | D83: ETH | E83: 0 | F83: Traded for Lunacian Item | G83: 0.002 | H83: ='Crypto Ledger Wallet'!$G83*'Crypto Market Price Data'!$C$6 -> 5.48118 | I83: ='Crypto Ledger Wallet'!$H83 -> 5.48118
A84: Asset 4 | B84: x1 Axie for Lunachian: Blossom Tree | C84: Traded | D84: ETH | E84: 0 | F84: Traded for Lunacian Item | G84: 0.003 | H84: ='Crypto Ledger Wallet'!$G84*'Crypto Market Price Data'!$C$6 -> 8.22177 | I84: ='Crypto Ledger Wallet'!$H84 -> 8.22177
A85: Asset 5 | B85: x1 Axie: #10956255 | C85: 44593 | D85: ETH | E85: 1 | F85: 34.84 | G85: 0.015 | H85: ='Crypto Ledger Wallet'!$G85*'Crypto Market Price Data'!$C$6 -> 41.10885 | I85: ='Crypto Ledger Wallet'!$H85-'Crypto Ledger Wallet'!$F85 -> 6.26885
A86: Asset 6 | B86: x1 Axie: #4111591 | C86: 44593 | D86: ETH | E86: 1 | F86: 34.84 | G86: 0.015 | H86: ='Crypto Ledger Wallet'!$G86*'Crypto Market Price Data'!$C$6 -> 41.10885 | I86: ='Crypto Ledger Wallet'!$H86-'Crypto Ledger Wallet'!$F86 -> 6.26885
A87: Asset 7 | B87: x1 Axie: #8843491 | C87: 44594 | D87: ETH | E87: 1 | F87: 40.2 | G87: 0.02 | H87: ='Crypto Ledger Wallet'!$G87*'Crypto Market Price Data'!$C$6 -> 54.8118 | I87: ='Crypto Ledger Wallet'!$H87-'Crypto Ledger Wallet'!$F87 -> 14.6118
A88: Asset 8 | B88: x1 Axie: #6320936 | C88: 44594 | D88: ETH | E88: 1 | F88: 40.2 | G88: 0.02 | H88: ='Crypto Ledger Wallet'!$G88*'Crypto Market Price Data'!$C$6 -> 54.8118 | I88: ='Crypto Ledger Wallet'!$H88-'Crypto Ledger Wallet'!$F88 -> 14.6118
A89: Asset 9 | B89: x1 Axie: #5178836 | C89: 44594 | D89: ETH | E89: 1 | F89: 32.16 | G89: 0.02 | H89: ='Crypto Ledger Wallet'!$G89*'Crypto Market Price Data'!$C$6 -> 54.8118 | I89: ='Crypto Ledger Wallet'!$H89-'Crypto Ledger Wallet'!$F89 -> 22.6518
A90: Asset 10 | B90: x1 Axie: #10933219 | C90: 44594 | D90: ETH | E90: 1 | F90: 88.44 | G90: 0.05 | H90: ='Crypto Ledger Wallet'!$G90*'Crypto Market Price Data'!$C$6 -> 137.0295 | I90: ='Crypto Ledger Wallet'!$H90-'Crypto Ledger Wallet'!$F90 -> 48.5895
A91: Asset 11 | B91: x1 Axie: #4014808 | C91: 44594 | D91: ETH | E91: 1 | F91: 29.48 | G91: 0.015 | H91: ='Crypto Ledger Wallet'!$G91*'Crypto Market Price Data'!$C$6 -> 41.10885 | I91: ='Crypto Ledger Wallet'!$H91-'Crypto Ledger Wallet'!$F91 -> 11.62885
A92: Asset 12 | B92: x1 Land: | C92: 44038 | D92: ETH | E92: 3 | F92: 150 | G92: 1.5 | H92: ='Crypto Ledger Wallet'!$G92*'Crypto Market Price Data'!$C$6 -> 4110.885 | I92: ='Crypto Ledger Wallet'!$H92-'Crypto Ledger Wallet'!$F92 -> 3960.885
A93: League of Kingdoms
A94: Asset 1 | B94: x1 Lvl 3 Land: #139483 | C94: 44643 | D94: ETH | E94: 28 | F94: 500 | G94: 0.2 | H94: ='Crypto Ledger Wallet'!$G94*'Crypto Market Price Data'!$C$6 -> 548.118 | I94: ='Crypto Ledger Wallet'!$H94-'Crypto Ledger Wallet'!$F94 -> 48.118
A95: Asset 2 | B95: x1 Lvl 2 Land: #139484 | C95: 44643 | D95: ETH | E95: 12 | F95: 450 | G95: 0.15 | H95: ='Crypto Ledger Wallet'!$G95*'Crypto Market Price Data'!$C$6 -> 411.0885 | I95: ='Crypto Ledger Wallet'!$H95-'Crypto Ledger Wallet'!$F95 -> -38.9115
A96: Asset 3 | B96: x4 Skins
A97: Townstar
A98: Asset 1 | B98: x2 Buggy Waterbot | C98: 44481 | D98: ETH | E98: 60 | F98: 230 | G98: 0.1 | H98: ='Crypto Ledger Wallet'!$G98*'Crypto Market Price Data'!$C$6 -> 274.059 | I98: ='Crypto Ledger Wallet'!$H98-'Crypto Ledger Wallet'!$F98 -> 44.059
A99: Asset 2 | B99: Express Depot | C99: 44699 | D99: GALA | E99: 0 | F99: 0 | G99: 249 | H99: ='Crypto Ledger Wallet'!$G99*'Crypto Market Price Data'!$C$21 -> 1.6715096 | I99: ='Crypto Ledger Wallet'!$H99-'Crypto Ledger Wallet'!$F99 -> 1.6715096
A100: Asset 3 | B100: Flour Storage | C100: 44722 | D100: GALA | E100: 0 | F100: 0 | G100: 140 | H100: ='Crypto Ledger Wallet'!$G100*'Crypto Market Price Data'!$C$21 -> 0.9398046 | I100: ='Crypto Ledger Wallet'!$H100-'Crypto Ledger Wallet'!$F100 -> 0.9398046
A101: Spider Tanks | I101: ='Crypto Ledger Wallet'!$H101-'Crypto Ledger Wallet'!$F101 -> 0
...

Sheet Expenses
A1: Fincancial Portfolio: Expense Data
A2: Expenses
A5: June 2022 Expenses | F5: July 2022 Expenses | K5: August 2022 Expenses | P5: September 2022 Expenses | U5: October 2022 Expenses | Z5: Nobember 2022 Expenses | AE5: December 2022 Expenses | AJ5: January 2023 Expenses | AO5: February 2023 Expenses | AT5: March 2023 Expenses | AY5: April 2023 Expenses | BD5: May 2023 Expenses
A7: Errands | B7: Date | C7: Amount | D7: Notes | F7: Errands | G7: Date | H7: Amount | I7: Notes | K7: Errands | L7: Date | M7: Amount | N7: Notes | P7: Errands | Q7: Date | R7: Amount | S7: Notes | U7: Errands | V7: Date | W7: Amount | X7: Notes | Z7: Errands | AA7: Date | AB7: Amount | AC7: Notes | AE7: Errands | AF7: Date | AG7: Amount | AH7: Notes | AJ7: Errands | AK7: Date | AL7: Amount | AM7: Notes | AO7: Errands | AP7: Date | AQ7: Amount | AR7: Notes | AT7: Errands | AU7: Date | AV7: Amount | AW7: Notes | AY7: Errands | AZ7: Date | BA7: Amount | BB7: Notes | BD7: Errands | BE7: Date | BF7: Amount | BG7: Notes
A8: Dad | B8: 44715 | C8: 20 | F8: Mom: Picked up Car | G8: 44748 | H8: 35 | I8: - In Gas | K8: Dad | L8: 44800 | M8: 20 | P8: Dad | Q8: 44805 | R8: 20 | U8: Dad | V8: 44835 | W8: 40 | Z8: Dad | AA8: 44866 | AB8: 40 | AE8: Dad | AF8: 44896 | AG8: 40 | AJ8: Dad | AK8: 44927 | AL8: 40 | AO8: Dad | AP8: 44958 | AQ8: 40 | AT8: Dad | AU8: 44986 | AV8: 40 | AW8: - Estimate | AY8: Dad | AZ8: 45017 | BA8: 40 | BB8: - Estimate
A9: Lindsey | B9: 44716 | C9: -51.8 | F9: Country Boom Ride | G9: 44750 | H9: 20 | I9: - For Gas | P9: Dad | Q9: 44806 | R9: 20 | S9: - Food | AO9: Mom | AP9: 44985 | AQ9: 100 | AR9: - For Trip & Dog Poop | AT9: Dad | AU9: 44999 | AV9: 80 | AW9: - Estimate
A10: - Paid back | B10: 44716 | C10: 40 | H10: =SUM(H8:H9) -> 55 | M10: =SUM(M8:M9) -> 20 | R10: =SUM(R8:R9) -> 40 | W10: =SUM(W8:W9) -> 40 | AB10: =SUM(AB8:AB9) -> 40 | AG10: =SUM(AG8:AG9) -> 40 | AL10: =SUM(AL8:AL9) -> 40 | AQ10: =SUM(AQ8:AQ9) -> 140 | AV10: =SUM(AV8:AV9) -> 120 | BA10: =SUM(BA8:BA9) -> 40 | BF10: =SUM(BF8:BF9) -> 0
A11: Dad | B11: 44717 | C11: 18
A12: Dad | B12: 44718 | C12: 20
A13: Dad | B13: 44721 | C13: 20 | F13: Flights | G13: Date | H13: Amount | I13: Notes | K13: Flights | L13: Date | M13: Amount | N13: Notes | P13: Flights | Q13: Date | R13: Amount | S13: Notes | U13: Flights | V13: Date | W13: Amount | X13: Notes | Z13: Flights | AA13: Date | AB13: Amount | AC13: Notes | AE13: Flights | AF13: Date | AG13: Amount | AH13: Notes | AJ13: Flights | AK13: Date | AL13: Amount | AM13: Notes | AO13: Flights | AP13: Date | AQ13: Amount | AR13: Notes | AT13: Flights | AU13: Date | AV13: Amount | AW13: Notes | AY13: Flights | AZ13: Date | BA13: Amount | BB13: Notes | BD13: Flights | BE13: Date | BF13: Amount | BG13: Notes
A14: Dad | B14: 44723 | C14: 40 | P14: Plane Ticket | Q14: 44813 | R14: -376.2 | Z14: Flight | AA14: 44871 | AB14: -386.2
A15: Dad | B15: 44724 | C15: 25
A16: Dad | B16: 44729 | C16: 20 | H16: =SUM(H14:H15) -> 0 | M16: =SUM(M14:M15) -> 0 | R16: =SUM(R14:R15) -> -376.2 | W16: =SUM(W14:W15) -> 0 | AB16: =SUM(AB14:AB15) -> -386.2 | AG16: =SUM(AG14:AG15) -> 0 | AL16: =SUM(AL14:AL15) -> 0 | AQ16: =SUM(AQ14:AQ15) -> 0 | AV16: =SUM(AV14:AV15) -> 0 | BA16: =SUM(BA14:BA15) -> 0 | BF16: =SUM(BF14:BF15) -> 0
A17: Dad | B17: 44731 | C17: 20
A18: Dad | B18: 44735 | C18: 20
A19: Dad | B19: 44737 | C19: 20 | F19: Gas | G19: Date | H19: Amount | I19: Notes | K19: Gas | L19: Date | M19: Amount | N19: Notes | P19: Gas | Q19: Date | R19: Amount | S19: Notes | U19: Gas | V19: Date | W19: Amount | X19: Notes | Z19: Gas | AA19: Date | AB19: Amount | AC19: Notes | AE19: Gas | AF19: Date | AG19: Amount | AH19: Notes | AJ19: Gas | AK19: Date | AL19: Amount | AM19: Notes | AO19: Gas | AP19: Date | AQ19: Amount | AR19: Notes | AT19: Gas | AU19: Date | AV19: Amount | AW19: Notes | AY19: Gas | AZ19: Date | BA19: Amount | BB19: Notes | BD19: Gas | BE19: Date | BF19: Amount | BG19: Notes
C20: =SUM(C8:C19) -> 211.2 | F20: Kwik Trip | G20: 44743 | H20: -20.25 | K20: Kwik Trip | L20: 44774 | M20: -20 | P20: Kwik Trip | Q20: 44811 | R20: -20 | U20: Kwik Trip | V20: 44845 | W20: -40 | Z20: Kwik Trip | AA20: 44866 | AB20: -20 | AE20: Kwik Trip | AF20: 44903 | AG20: -25.05 | AJ20: Sun | AK20: 44927 | AL20: -32.31 | AO20: Kwik Trip | AP20: 44958 | AQ20: -25 | AT20: Kwik Trip | AU20: 44991 | AV20: -25.27 | AY20: Kwik Trip | AZ20: 45019 | BA20: -20 | BD20: Kwik Trip | BE20: 45056 | BF20: -30
F21: Kwik Trip | G21: 44750 | H21: -20.05 | K21: Kwik Trip | L21: 44776 | M21: -15 | P21: Kwik Trip | Q21: 44812 | R21: -25 | U21: Kwik Trip | V21: 44852 | W21: -40 | Z21: Kwik Trip | AA21: 44873 | AB21: -20 | AE21: Kwik Trip | AF21: 44908 | AG21: -20 | AJ21: Wawa | AK21: 44932 | AL21: -21.8 | AO21: Kwik Trip | AP21: 44963 | AQ21: -25 | AT21: Kwik Trip | AU21: 44996 | AV21: -40 | AY21: Kwik Trip | AZ21: 45023 | BA21: -25.05 | BD21: Kwik Trip | BE21: 45061 | BF21: -25
F22: Kwik Trip | G22: 44755 | H22: -20 | K22: Kwik Trip | L22: 44785 | M22: -25 | P22: Kwik Trip | Q22: 44823 | R22: -20 | U22: Kwik Trip | V22: 44858 | W22: -35 | Z22: Kwik Trip | AA22: 44878 | AB22: -20.05 | AE22: Kwik Trip | AF22: 44910 | AG22: -30.01 | AJ22: Wawa | AK22: 44932 | AL22: -23.41 | AO22: Kwik Trip | AP22: 44966 | AQ22: -20.25 | AT22: Kwik Trip | AU22: 44996 | AV22: -20 | AY22: Kwik Trip | AZ22: 45029 | BA22: -21 | BD22: Kwik Trip | BE22: 45065 | BF22: -20
A23: Flights | B23: Date | C23: Amount | D23: Notes | F23: Kwik Trip | G23: 44760 | H23: -15 | K23: Kwik Trip | L23: 44788 | M23: -18 | P23: Kwik Trip | Q23: 44828 | R23: -20.01 | W23: =SUM(W20:W22) -> -115 | Z23: Kwik Trip | AA23: 44883 | AB23: -30 | AE23: Kwik Trip | AF23: 44915 | AG23: -25 | AJ23: Circle K | AK23: 44939 | AL23: -29.61 | AO23: Kwik Trip | AP23: 44972 | AQ23: -30 | AT23: Kwik Trip | AU23: 45000 | AV23: -20 | BA23: =SUM(BA20:BA22) -> -66.05 | BD23: Kwik Trip | BE23: 45068 | BF23: -20
F24: Kwik Trip | G24: 44767 | H24: -20 | K24: Kwik Trip | L24: 44793 | M24: -15.75 | P24: Kwik Trip | Q24: 44831 | R24: -25 | Z24: Kwik Trip | AA24: 44895 | AB24: -20 | AE24: Kwik Trip | AF24: 44918 | AG24: -25 | AJ24: Kwik Trip | AK24: 44951 | AL24: -30 | AO24: Kwik Trip | AP24: 44978 | AQ24: -30 | AT24: Kwik Trip | AU24: 45005 | AV24: -20 | BD24: Kwik Trip | BE24: 45076 | BF24: -25.01
H25: =SUM(H20:H24) -> -95.3 | K25: Kwik Trip | L25: 44794 | M25: -20 | R25: =SUM(R20:R24) -> -110.01 | AB25: =SUM(AB20:AB24) -> -110.05 | AE25: Kwik Trip | AF25: 44918 | AG25: -20 | AL25: =SUM(AL20:AL24) -> -137.13 | AO25: Kwik Trip | AP25: 44984 | AQ25: -45 | AR25: - Trip | AT25: Kwik Trip | AU25: 45009 | AV25: -20 | BF25: =SUM(BF20:BF24) -> -120.01
C26: =SUM(C24:C25) -> 0 | M26: =SUM(M20:M25) -> -113.75 | U26: Gas Stations | V26: Date | W26: Amount | X26: Notes | AG26: =SUM(AG20:AG25) -> -145.06 | AQ26: =SUM(AQ20:AQ25) -> -175.25 | AT26: Kwik Trip | AU26: 45012 | AV26: -20 | AY26: Gas Stations | AZ26: Date | BA26: Amount | BB26: Notes
U27: Kwik Trip | V27: 44835 | W27: -3.37 | AV27: =SUM(AV20:AV26) -> -165.27 | AY27: Kwik Trip | AZ27: 45017 | BA27: -5.26
F28: Gas Stations | G28: Date | H28: Amount | I28: Notes | P28: Gas Stations | Q28: Date | R28: Amount | S28: Notes | U28: Kwik Trip | V28: 44836 | W28: -7.58 | Z28: Gas Stations | AA28: Date | AB28: Amount | AC28: Notes | AJ28: Gas Stations | AK28: Date | AL28: Amount | AM28: Notes | AY28: Kwik Trip | AZ28: 45019 | BA28: -5.26 | BD28: Gas Stations | BE28: Date | BF28: Amount | BG28: Notes
A29: Gas | B29: Date | C29: Amount | D29: Notes | F29: Kwik Trip | G29: 44743 | H29: -6.33 | K29: Gas Stations | L29: Date | M29: Amount | N29: Notes | P29: Kwik Trip | Q29: 44806 | R29: -11.09 | U29: Kwik Trip | V29: 44838 | W29: -4.21 | Z29: Kwik Trip | AA29: 44866 | AB29: -4.73 | AE29: Gas Stations | AF29: Date | AG29: Amount | AH29: Notes | AJ29: Circle K | AK29: 44939 | AL29: -47.82 | AO29: Gas Stations | AP29: Date | AQ29: Amount | AR29: Notes | AY29: Kwik Trip | AZ29: 45023 | BA29: -5.26 | BD29: Kwik Trip | BE29: 45047 | BF29: -2.98
A30: Kwik Trip | B30: 44720 | C30: -15 | F30: Kwik Trip | G30: 44744 | H30: -10.52 | K30: Kwik Trip | L30: 44777 | M30: -5.99 | P30: Kwik Trip | Q30: 44808 | R30: -8.1 | U30: Kwik Trip | V30: 44838 | W30: -3.37 | Z30: Kwik Trip | AA30: 44869 | AB30: -8.92 | AE30: Kwik Trip | AF30: 44899 | AG30: -6.31 | AJ30: Kwik Trip | AK30: 44942 | AL30: -7.25 | AO30: Kwik Trip | AP30: 44958 | AQ30: -5.26 | AT30: Gas Stations | AU30: Date | AV30: Amount | AW30: Notes | AY30: Kwik Trip | AZ30: 45029 | BA30: -5.26 | BD30: Kwik Trip | BE30: 45049 | BF30: -5.26
A31: Kwik Trip | B31: 44721 | C31: -25 | F31: Kwik Trip | G31: 44746 | H31: -6.33 | K31: Kwik Trip | L31: 44777 | M31: -9.82 | P31: Kwik Trip | Q31: 44811 | R31: -3.37 | U31: Kwik Trip | V31: 44839 | W31: -8.4 | Z31: Kwik Trip | AA31: 44871 | AB31: -4.21 | AE31: Kwik Trip | AF31: 44903 | AG31: -4.73 | AJ31: Kwik Trip | AK31: 44948 | AL31: -9.45 | AO31: Kwik Trip | AP31: 44963 | AQ31: -7.05 | AT31: Kwik Trip | AU31: 44991 | AV31: -7.25 | AY31: Kwik Trip | AZ31: 45031 | BA31: -8.82 | BD31: Kwik Trip | BE31: 45049 | BF31: -8.82
A32: Kwik Trip | B32: 44726 | C32: -20 | F32: Kwik Trip | G32: 44746 | H32: -6.4 | K32: Kwik Trip | L32: 44780 | M32: -6.81 | P32: Kwik Trip | Q32: 44812 | R32: -6.08 | U32: Kwik Trip | V32: 44840 | W32: -6.9 | Z32: Kwik Trip | AA32: 44873 | AB32: -7.36 | AE32: Kwik Trip | AF32: 44903 | AG32: -5.99 | AJ32: Kwik Trip | AK32: 44949 | AL32: -25.26 | AO32: Kwik Trip | AP32: 44969 | AQ32: -2.83 | AT32: Kwik Trip | AU32: 44993 | AV32: -5.26 | AY32: Kwik Trip | AZ32: 45035 | BA32: -12.19 | BD32: Kwik Trip | BE32: 45052 | BF32: -11.25
A33: Kwik Trip | B33: 44729 | C33: -25.3 | F33: Kwik Trip | G33: 44747 | H33: -10.4 | K33: Kwik Trip | L33: 44782 | M33: -7.56 | P33: Kwik Trip | Q33: 44814 | R33: -6.81 | U33: Kwik Trip | V33: 44841 | W33: -11.09 | Z33: Kwik Trip | AA33: 44873 | AB33: -8.19 | AE33: Kwik Trip | AF33: 44905 | AG33: -12.18 | AJ33: Kwik Trip | AK33: 44950 | AL33: -5.26 | AO33: Kwik Trip | AP33: 44970 | AQ33: -4.73 | AT33: Kwik Trip | AU33: 44994 | AV33: -8.82 | AY33: Kwik Trip | AZ33: 45037 | BA33: -13.34 | BD33: Kwik Trip | BE33: 45054 | BF33: -8.24
A34: Kwik Trip | B34: 44730 | C34: -20 | F34: Kwik Trip | G34: 44748 | H34: -17.04 | K34: Kwik Trip | L34: 44782 | M34: -4 | P34: Kwik Trip | Q34: 44816 | R34: -5.99 | U34: Kwik Trip | V34: 44843 | W34: -11.62 | Z34: Kwik Trip | AA34: 44875 | AB34: -4.21 | AE34: Kwik Trip | AF34: 44910 | AG34: -4.21 | AJ34: Kwik Trip | AK34: 44951 | AL34: -4.73 | AO34: Kwik Trip | AP34: 44974 | AQ34: -11.25 | AT34: Kwik Trip | AU34: 44995 | AV34: -8.82 | AY34: Kwik Trip | AZ34: 45042 | BA34: -5.99 | BD34: Kwik Trip | BE34: 45063 | BF34: -8.1
C35: =SUM(C30:C34) -> -105.3 | F35: Kwik Trip | G35: 44749 | H35: -5.78 | K35: Kwik Trip | L35: 44787 | M35: -11.41 | P35: Kwik Trip | Q35: 44816 | R35: -8.4 | U35: Kwik Trip | V35: 44843 | W35: -7.88 | Z35: Kwik Trip | AA35: 44875 | AB35: -6.81 | AE35: Kwik Trip | AF35: 44915 | AG35: -4.73 | AJ35: Kwik Trip | AK35: 44951 | AL35: -5.99 | AO35: Kwik Trip | AP35: 44975 | AQ35: -16.25 | AT35: Kwik Trip | AU35: 44997 | AV35: -8.82 | AY35: Kwik Trip | AZ35: 45043 | BA35: -5.26 | BD35: Kwik Trip | BE35: 45065 | BF35: -14.09
F36: Kwik Trip | G36: 44750 | H36: -5.39 | K36: Kwik Trip | L36: 44790 | M36: -5.99 | P36: Kwik Trip | Q36: 44817 | R36: -9.14 | U36: Kwik Trip | V36: 44844 | W36: -8.4 | Z36: Kwik Trip | AA36: 44877 | AB36: -13.99 | AE36: Kwik Trip | AF36: 44921 | AG36: -15.5 | AJ36: Kwik Trip | AK36: 44952 | AL36: -5.26 | AO36: Kwik Trip | AP36: 44977 | AQ36: -6.73 | AT36: Kwik Trip | AU36: 45000 | AV36: -3.14 | BA36: =SUM(BA27:BA35) -> -66.64 | BD36: Kwik Trip | BE36: 45068 | BF36: -16.37
F37: Kwik Trip | G37: 44751 | H37: -10.05 | K37: Kwik Trip | L37: 44793 | M37: -4.2 | P37: Kwik Trip | Q37: 44822 | R37: -2.62 | U37: Kwik Trip | V37: 44844 | W37: -7.58 | Z37: Kwik Trip | AA37: 44880 | AB37: -4.21 | AE37: Kwik Trip | AF37: 44921 | AG37: -22.63 | AJ37: Kwik Trip | AK37: 44955 | AL37: -12.41 | AO37: Kwik Trip | AP37: 44981 | AQ37: -5.26 | AT37: Kwik Trip | AU37: 45005 | AV37: -5.26 | BD37: Kwik Trip | BE37: 45071 | BF37: -6.99
A38: Gas Station Items | B38: Date | C38: Amount | D38: Notes | F38: Kwik Trip | G38: 44752 | H38: -17.94 | K38: Kwik Trip | L38: 44798 | M38: -18.99 | P38: Kwik Trip | Q38: 44824 | R38: -7.58 | U38: Kwik Trip | V38: 44845 | W38: -6.73 | Z38: Kwik Trip | AA38: 44882 | AB38: -5.25 | AE38: Kwik Trip | AF38: 44921 | AG38: -12.22 | AJ38: Kwik Trip | AK38: 44956 | AL38: -5.26 | AO38: Kwik Trip | AP38: 44984 | AQ38: -5.26 | AT38: Kwik Trip | AU38: 45005 | AV38: -11.25 | BD38: Kwik Trip | BE38: 45073 | BF38: -5.26
A39: Kwik Trip | B39: 44713 | C39: -9.27 | F39: Kwik Trip | G39: 44753 | H39: -4.52 | K39: Kwik Trip | L39: 44800 | M39: -4.31 | P39: Kwik Trip | Q39: 44824 | R39: -6.62 | U39: Kwik Trip | V39: 44852 | W39: -5.99 | Z39: Kwik Trip | AA39: 44883 | AB39: -2.62 | AE39: Kwik Trip | AF39: 44924 | AG39: -7.15 | AL39: =SUM(AL29:AL38) -> -128.69 | AO39: Kwik Trip | AP39: 44984 | AQ39: -7.79 | AT39: Kwik Trip | AU39: 45010 | AV39: -5.26 | AY39: Reg Store | AZ39: Date | BA39: Amount | BB39: Notes | BD39: Kwik Trip | BE39: 45073 | BF39: -5.26
A40: Kwik Trip | B40: 44714 | C40: -5.78 | F40: Kwik Trip | G40: 44753 | H40: -4.21 | K40: Kwik Trip | L40: 44803 | M40: -6.81 | P40: Kwik Trip | Q40: 44825 | R40: -3.37 | U40: Kwik Trip | V40: 44852 | W40: -7.56 | Z40: Kwik Trip | AA40: 44884 | AB40: -2.62 | AE40: Kwik Trip | AF40: 44925 | AG40: -5.26 | AQ40: =SUM(AQ30:AQ39) -> -72.41 | AT40: Kwik Trip | AU40: 45011 | AV40: -11.25 | AY40: Walmart | AZ40: 45020 | BA40: -19.51 | BF40: =SUM(BF29:BF39) -> -92.62
A41: Kwik Trip | B41: 44715 | C41: -6.64 | F41: Kwik Trip | G41: 44754 | H41: -2.31 | M41: =SUM(M30:M40) -> -85.89 | P41: Kwik Trip | Q41: 44828 | R41: -4.73 | U41: Kwik Trip | V41: 44854 | W41: -4.73 | Z41: Kwik Trip | AA41: 44886 | AB41: -4.21 | AE41: Kwik Trip | AF41: 44926 | AG41: -5.26 | AT41: Kwik Trip | AU41: 45012 | AV41: -5.26 | AY41: Walmart | AZ41: 45021 | BA41: -22.08
A42: Kwik Trip | B42: 44716 | C42: -4.21 | F42: Kwik Trip | G42: 44754 | H42: -8.83 | P42: Kwik Trip | Q42: 44829 | R42: -8.4 | U42: Kwik Trip | V42: 44854 | W42: -7.88 | Z42: Kwik Trip | AA42: 44888 | AB42: -6.81 | AG42: =SUM(AG30:AG41) -> -106.17 | AJ42: Reg Store | AK42: Date | AL42: Amount | AM42: Notes | AT42: Kwik Trip | AU42: 45013 | AV42: -8.82 | AY42: Office Depot | AZ42: 45026 | BA42: -10.54
A43: Kwik Trip | B43: 44719 | C43: -4.21 | F43: Kwik Trip | G43: 44755 | H43: -4.64 | P43: Kwik Trip | Q43: 44830 | R43: -3.37 | U43: Kwik Trip | V43: 44856 | W43: -8.4 | Z43: Kwik Trip | AA43: 44890 | AB43: -4.21 | AJ43: Publix | AK43: 44931 | AL43: -16.13 | AO43: Reg Store | AP43: Date | AQ43: Amount | AR43: Notes | AT43: Kwik Trip | AU43: 45014 | AV43: -14.78 | AY43: Walmart | AZ43: 45026 | BA43: -17.22 | BD43: Reg Store | BE43: Date | BF43: Amount | BG43: Notes
A44: Kwik Trip | B44: 44720 | C44: -5.89 | F44: Kwik Trip | G44: 44755 | H44: -2.69 | K44: Reg Store | L44: Date | M44: Amount | N44: Notes | P44: Kwik Trip | Q44: 44831 | R44: -10.41 | U44: Kwik Trip | V44: 44858 | W44: -8.1 | Z44: Kwik Trip | AA44: 44894 | AB44: -4.73 | AJ44: Publix | AK44: 44931 | AL44: -9.22 | AO44: Walmart | AP44: 44959 | AQ44: -29.97 | AV44: =SUM(AV31:AV43) -> -103.99 | AY44: Walmart | AZ44: 45027 | BA44: -20.97 | BD44: Walmart | BE44: 45047 | BF44: -11.78
A45: Kwik Trip | B45: 44722 | C45: -6.31 | F45: Kwik Trip | G45: 44759 | H45: -4.88 | K45: Walmart | L45: 44780 | M45: -21.16 | P45: Kwik Trip | Q45: 44832 | R45: -6.51 | U45: Kwik Trip | V45: 44859 | W45: -6.51 | Z45: Kwik Trip | AA45: 44895 | AB45: -4.73 | AE45: Reg Store | AF45: Date | AG45: Amount | AH45: Notes | AJ45: Publix | AK45: 44935 | AL45: -20.09 | AO45: Walgreens | AP45: 44962 | AQ45: -23.2 | AR45: - Flowers | AY45: Walmart | AZ45: 45029 | BA45: -11.27 | BD45: Walmart | BE45: 45054 | BF45: -19.71
A46: Kwik Trip | B46: 44724 | C46: -4.21 | F46: Kwik Trip | G46: 44760 | H46: -4.88 | K46: Festival | L46: 44788 | M46: -17.91 | P46: Kwik Trip | Q46: 44833 | R46: -4.73 | U46: Kwik Trip | V46: 44861 | W46: -3.89 | AB46: =SUM(AB29:AB45) -> -97.81 | AE46: Walmart | AF46: 44900 | AG46: -27.39 | AJ46: Trader Joe's | AK46: 44937 | AL46: -43.58 | AO46: Walmart | AP46: 44964 | AQ46: -3.17 | AY46: Walmart | AZ46: 45033 | BA46: -19.43 | BD46: Ace Hardware | BE46: 45054 | BF46: -18.98
A47: Kwik Trip | B47: 44726 | C47: -12.3 | F47: Kwik Trip | G47: 44763 | H47: -4.21 | K47: Walmart | L47: 44793 | M47: -26.5 | R47: =SUM(R29:R46) -> -117.32 | U47: Kwik Trip | V47: 44861 | W47: -8.4 | AE47: Festival | AF47: 44917 | AG47: -31.67 | AJ47: Walmart | AK47: 44942 | AL47: -19.98 | AO47: Walmart | AP47: 44964 | AQ47: -14.82 | AT47: Reg Store | AU47: Date | AV47: Amount | AW47: Notes | AY47: Walmart | AZ47: 45043 | BA47: -53.54 | BD47: Etsy | BE47: 45062 | BF47: -28.96
A48: Kwik Trip | B48: 44726 | C48: -4.81 | F48: Kwik Trip | G48: 44764 | H48: -13.17 | K48: Walmart | L48: 44796 | M48: -13.6 | U48: Kwik Trip | V48: 44862 | W48: -3.37 | AE48: Walmart | AF48: 44926 | AG48: -39.54 | AJ48: Walmart | AK48: 44948 | AL48: -10.96 | AO48: Walmart | AP48: 44970 | AQ48: -19.64 | AT48: CVS | AU48: 44988 | AV48: -17.78 | AW48: - Trip | AY48: Walmart | AZ48: 45046 | BA48: -10.15 | BD48: Walmart | BE48: 45071 | BF48: -134.79
A49: Kwik Trip | B49: 44728 | C49: -3.15 | F49: Kwik Trip | G49: 44765 | H49: -10.92 | K49: Festival | L49: 44788 | M49: -10 | U49: Kwik Trip | V49: 44862 | W49: -4.73 | Z49: Reg Store | AA49: Date | AB49: Amount | AC49: Notes | AG49: =SUM(AG46:AG48) -> -98.6 | AJ49: Walmart | AK49: 44957 | AL49: -52.15 | AO49: Walmart | AP49: 44977 | AQ49: -16.12 | AT49: Publix | AU49: 44990 | AV49: -82.39 | AW49: - Trip | BA49: =SUM(BA40:BA48) -> -184.71 | BF49: =SUM(BF44:BF48) -> -214.22
A50: Kwik Trip | B50: 44728 | C50: -4.81 | F50: Kwik Trip | G50: 44766 | H50: -9.5 | K50: Walmart | L50: 44797 | M50: -9.08 | P50: Reg Store | Q50: Date | R50: Amount | S50: Notes | U50: Kwik Trip | V50: 44863 | W50: -11.55 | Z50: Walmart | AA50: 44866 | AB50: -22.87 | AL50: =SUM(AL43:AL49) -> -172.11 | AO50: Walmart | AP50: 44984 | AQ50: -10.63 | AT50: Farmers Market CLT | AU50: 44991 | AV50: -11.9 | AW50: - Trip
A51: Kwik Trip | B51: 44729 | C51: -6.31 | F51: Kwik Trip | G51: 44767 | H51: -13 | M51: =SUM(M45:M50) -> -98.25 | P51: Walmart | Q51: 44809 | R51: -13.19 | W51: =SUM(W27:W50) -> -168.24 | Z51: Walmart | AA51: 44874 | AB51: -17.92 | AQ51: =SUM(AQ44:AQ50) -> -117.55 | AT51: Walmart | AU51: 44991 | AV51: -3.37
A52: Kwik Trip | B52: 44730 | C52: -6.31 | F52: Kwik Trip | G52: 44770 | H52: -9.78 | P52: Walmart | Q52: 44812 | R52: -13.13 | S52: - Cash | Z52: Walmart | AA52: 44882 | AB52: -14.43 | AE52: Restuarants | AF52: Date | AG52: Amount | AH52: Notes | AT52: GNC | AU52: 45003 | AV52: -84.39 | AY52: Restuarants | AZ52: Date | BA52: Amount | BB52: Notes | BD52: Restuarants | BE52: Date | BF52: Amount | BG52: Notes
A53: Kwik Trip | B53: 44730 | C53: -1.99 | F53: Kwik Trip | G53: 44771 | H53: -3.37 | P53: Walmart | Q53: 44817 | R53: -27.43 | AB53: =SUM(AB50:AB52) -> -55.22 | AE53: Caribou Coffee | AF53: 44896 | AG53: -7.51 | AJ53: Restuarants | AK53: Date | AL53: Amount | AM53: Notes | AT53: Walmart | AU53: 45003 | AV53: -69.47 | AY53: Caribou | AZ53: 45019 | BA53: -7.75 | BD53: State Room | BE53: 45049 | BF53: 23
A54: Kwik Trip | B54: 44731 | C54: -4.21 | F54: Kwik Trip | G54: 44771 | H54: -6.9 | K54: Restuarants | L54: Date | M54: Amount | N54: Notes | P54: Walmart | Q54: 44819 | R54: -19 | U54: Reg Store | V54: Date | W54: Amount | X54: Notes | AE54: The Crow (Work) | AF54: 44897 | AG54: -13 | AJ54: Airport (Snacks) | AK54: 44927 | AL54: -50.72 | AM54: - Trip | AO54: Restuarants | AP54: Date | AQ54: Amount | AR54: Notes | AT54: GNC | AU54: 45005 | AV54: -79.11 | AY54: Chick Fil A | AZ54: 45025 | BA54: -11.34 | BD54: The Crow | BE54: 45049 | BF54: 19.4
A55: Kwik Trip | B55: 44732 | C55: -7.36 | F55: Other Gas Station | G55: 44772 | H55: -7.3 | K55: The Crow (Work) | L55: 44775 | M55: -6.5 | P55: Walmart | Q55: 44824 | R55: -10.83 | U55: Walmart | V55: 44839 | W55: -13.19 | AE55: The Crow (Work) | AF55: 44899 | AG55: -6.32 | AJ55: Airport (Snacks) | AK55: 44927 | AL55: -15.39 | AM55: - Trip | AO55: The Crow (Work) | AP55: 44958 | AQ55: -5.95 | AT55: Walgreens | AU55: 45005 | AV55: -27.42 | AY55: Caribou | AZ55: 45029 | BA55: -7.75 | BD55: The Crow | BE55: 45049 | BF55: 25.84
A56: Kwik Trip | B56: 44733 | C56: -3.15 | H56: =SUM(H29:H55) -> -211.29 | K56: The Crow (Work) | L56: 44778 | M56: -15.06 | P56: Walmart | Q56: 44828 | R56: -21.73 | U56: Walmart | V56: 44845 | W56: -19.1 | Z56: Restuarants | AA56: Date | AB56: Amount | AC56: Notes | AE56: Caribou Coffee | AF56: 44902 | AG56: -7.51 | AJ56: Catalina Cafe | AK56: 44928 | AL56: -28.76 | AM56: - Trip | AO56: Caribou | AP56: 44959 | AQ56: -6.74 | AT56: Walmart | AU56: 45014 | AV56: -40.01 | AY56: Pettibone BH | AZ56: 45030 | BA56: -45.3 | BD56: Caribou | BE56: 45050 | BF56: -7.75
A57: Kwik Trip | B57: 44733 | C57: -13.09 | K57: Lovechild | L57: 44779 | M57: -118.42 | N57: - Date Night | P57: Walmart | Q57: 44832 | R57: -17.08 | U57: CVS | V57: 44848 | W57: -18.26 | X57: - Florida | Z57: Caribou Coffee | AA57: 44868 | AB57: -6.53 | AE57: Caribou Coffee | AF57: 44903 | AG57: -6.53 | AJ57: Gordos | AK57: 44930 | AL57: -27.34 | AM57: - Trip | AO57: The Crow (Work) | AP57: 44959 | AQ57: -58.39 | AR57: - Thursday w/ Will | AT57: Walmart | AU57: 45015 | AV57: -20.91 | AY57: Twisted Moose | AZ57: 45045 | BA57: -6.68 | BB57: - Bars | BD57: Culvers | BE57: 45148 | BF57: -4.53
A58: Kwik Trip | B58: 44734 | C58: -5.78 | K58: Big Als | L58: 44785 | M58: -42 | R58: =SUM(R51:R57) -> -122.39 | U58: Walmart | V58: 44858 | W58: -27.89 | Z58: The Crow (Work) | AA58: 44869 | AB58: -18.24 | AE58: The Crow (Work) | AF58: 44904 | AG58: -13 | AJ58: The Edison Restaurant | AK58: 44931 | AL58: -60 | AM58: - Trip | AO58: The Crow (Work) | AP58: 44961 | AQ58: -28.51 | AV58: =SUM(AV48:AV57) -> -436.75 | AY58: Twisted Moose | AZ58: 45045 | BA58: -6.24 | BD58: The Crow | BE58: 45148 | BF58: -50.63
A59: Kwik Trip | B59: 44734 | C59: -4.88 | F59: Reg Store | G59: Date | H59: Amount | I59: Notes | K59: Tea Shop UWL | L59: 44785 | M59: -26.52 | W59: =SUM(W55:W58) -> -78.44 | Z59: Twisted Moose | AA59: 44870 | AB59: -11.36 | AE59: Mexical | AF59: 44907 | AG59: -54.33 | AH59: - Date Night | AJ59: Tin & Lizzys | AK59: 44932 | AL59: -48.47 | AM59: - Trip | AO59: Caribou | AP59: 44962 | AQ59: -6.74 | BA59: =SUM(BA53:BA58) -> -85.06 | BD59: Apothic Eatery | BE59: 45151 | BF59: -49.34
A60: Kwik Trip | B60: 44737 | C60: -3.89 | F60: Walmart | G60: 44755 | H60: -4.81 | K60: The Crow (Work) | L60: 44789 | M60: -7.04 | Z60: The Crow (Work) | AA60: 44871 | AB60: -6.5 | AE60: The Crow (Fun) | AF60: 44909 | AG60: 42.41 | AH60: - Wingo | AJ60: The Edison Restaurant | AK60: 44932 | AL60: -14.16 | AM60: - Trip | AO60: The Crow (Work) | AP60: 44962 | AQ60: -6.5 | BD60: Dels | BE60: 45061 | BF60: -43
A61: Kwik Trip | B61: 44740 | C61: -2.62 | F61: Walmart | G61: 44761 | H61: -33.11 | K61: The Crow (Work) | L61: 44790 | M61: -6.85 | P61: Restuarants | Q61: Date | R61: Amount | S61: Notes | Z61: The Crow (Work) | AA61: 44873 | AB61: -6.5 | AE61: Caribou Coffee | AF61: 44909 | AG61: -24.55 | AJ61: Chipotle | AK61: 44935 | AL61: -3.28 | AM61: - Trip | AO61: Shogun | AP61: 44966 | AQ61: -33 | AR61: - Virtual Date Night | AT61: Restuarants | AU61: Date | AV61: Amount | AW61: Notes | BD61: McDonalds | BE61: 45061 | BF61: -5.39
C62: =SUM(C39:C61) -> -131.18 | F62: Woodmans | G62: 44762 | H62: -10.87 | K62: The Crow (Work) | L62: 44791 | M62: -4.33 | P62: The Crow (Work) | Q62: 44805 | R62: -7.04 | U62: Restuarants | V62: Date | W62: Amount | X62: Notes | Z62: The Crow (Work) | AA62: 44878 | AB62: -6.5 | AE62: The Crow (Work) | AF62: 44911 | AG62: -6.5 | AJ62: Over Under Bar | AK62: 44937 | AL62: -114.6 | AM62: - Trip | AO62: Caribou | AP62: 44966 | AQ62: -8.36 | AT62: The Pallace Saloon | AU62: 44986 | AV62: -20 | AW62: - Trip | AY62: Bars | AZ62: Date | BA62: Amount | BB62: Notes | BD62: Distilling Co. | BE62: 45061 | BF62: -95.81
H63: =SUM(H60:H62) -> -48.79 | K63: Caribou Coffee | L63: 44732 | M63: -11.5 | N63: - Cash | P63: McDonalds | Q63: 44807 | R63: -10.53 | U63: Qdoba | V63: 44836 | W63: -10.81 | Z63: Caribou Coffee | AA63: 44880 | AB63: -7.51 | AE63: Love Child | AF63: 44914 | AG63: -137.89 | AH63: - Date Night | AJ63: Little Masa | AK63: 44938 | AL63: -33.38 | AM63: - Trip | AO63: Caribou | AP63: 44973 | AQ63: -7.75 | AT63: Brick House | AU63: 44987 | AV63: -62.5 | AW63: - Trip | AY63: Week 1-2: | BD63: Waterfront | BE63: 45063 | BF63: -85
K64: The Crow (Work) | L64: 44795 | M64: -6.32 | P64: The Crow (Work) | Q64: 44809 | R64: -7.04 | U64: The Crow (Work) | V64: 44838 | W64: -24.62 | Z64: Caribou Coffee | AA64: 44882 | AB64: -7.51 | AE64: Charmont | AF64: 44914 | AG64: -32 | AH64: - Date Night | AJ64: Caribou Coffee | AK64: 44940 | AL64: -8.92 | AM64: - Trip | AO64: The Crow (Work) | AP64: 44973 | AQ64: -26.53 | AR64: - Thursday w/ Will | AT64: Bullwinkles | AU64: 44987 | AV64: -25.2 | AW64: - Trip | AY64: - Thurs-Fri | AZ64: 44986 | BA64: -80 | BD64: Waterfront | BE64: 45063 | BF64: -11
A65: Reg Store | B65: Date | C65: Amount | D65: Notes | K65: Qdoba | L65: 44797 | M65: -11.5 | P65: The Crow (Work) | Q65: 44810 | R65: -7.04 | S65: - Cash | U65: Caribou | V65: 44840 | W65: -14.54 | Z65: The Crow (Work) | AA65: 44885 | AB65: -6.5 | AE65: Top Shots | AF65: 44916 | AG65: -23 | AH65: - Night Out | AJ65: Airport (Snacks) | AK65: 44940 | AL65: -17.72 | AM65: - Trip | AO65: Blue Moon | AP65: 44975 | AQ65: -25 | AT65: Madison Social | AU65: 44987 | AV65: -12.9 | AW65: - Trip | AY65: Week 3-4: | BD65: Charmont | BE65: 45063 | BF65: -22
A66: Walmart | B66: 44719 | C66: -11.85 | D66: - Cash | F66: Restuarants | G66: Date | H66: Amount | I66: Notes | K66: The Crow (Work) | L66: 44799 | M66: -7.04 | P66: Caribou Coffee | Q66: 44810 | R66: -6.9 | U66: Politos | V66: 44843 | W66: -12.36 | Z66: The Crow (Work) | AA66: 44886 | AB66: -6.5 | AE66: The Crow (Fun) | AF66: 44916 | AG66: -30.9 | AH66: - Night Out | AJ66: Starbucks | AK66: 44940 | AL66: -6.85 | AM66: - Trip | AO66: The Crow (Work) | AP66: 44978 | AQ66: -20 | AT66: Madison Social | AU66: 44987 | AV66: -13.71 | AW66: - Trip | AY66: - Thurs - Sat | BA66: -80 | BD66: Double Barrel Tomah | BE66: 45065 | BF66: -38
A67: Walmart | B67: 44720 | C67: -4.39 | F67: The Crow (Work) | G67: 44743 | H67: -6.32 | K67: The Crow (Work) | L67: 44804 | M67: -7.04 | P67: Subway | Q67: 44811 | R67: -13.52 | U67: The Crow (Work) | V67: 44843 | W67: -11.5 | Z67: Caribou Coffee | AA67: 44888 | AB67: -6.53 | AE67: McDonalds | AF67: 44917 | AG67: -7.69 | AJ67: Caribou Coffee | AK67: 44949 | AL67: -7.75 | AO67: Caribou | AP67: 44981 | AQ67: -7.75 | AT67: Starbucks | AU67: 44987 | AV67: -16.57 | AW67: - Trip | BA67: =SUM(BA63:BA66) -> -160 | BD67: Java Vino | BE67: 45065 | BF67: -35.25
A68: Festival | B68: 44725 | C68: -7.99 | F68: Qdoba | G68: 44746 | H68: -23.16 | I68: - Chase Paid back $15 | M68: =SUM(M55:M67) -> -270.12 | P68: The Crow (Work) | Q68: 44811 | R68: -6.85 | U68: The Crow (Work) | V68: 44844 | W68: -6.5 | Z68: The Crow (Work) | AA68: 44892 | AB68: -19.2 | AE68: Bleu Duck | AF68: 44923 | AG68: -66.47 | AJ68: McDonalds | AK68: 44954 | AL68: -11.42 | AO68: MSN Café | AP68: 44985 | AQ68: -10.54 | AR68: - Trip | AT68: Poor Pauls | AU68: 44987 | AV68: -20.5 | AW68: - Trip | BD68: Pettibone Boat Club | BE68: 45067 | BF68: -60
A69: Walmart | B69: 44732 | C69: -22.53 | F69: The Crow (Work) | G69: 44748 | H69: -6.32 | P69: The Crow (Work) | Q69: 44813 | R69: -7.04 | U69: MSN Cafe | V69: 44846 | W69: -3.68 | X69: Trip - Madison | Z69: The Crow (Work) | AA69: 44893 | AB69: -6.5 | AE69: Charmont | AF69: 44924 | AG69: -142.06 | AH69: - Date Night | AJ69: The Crow (Work) | AK69: 44955 | AL69: -6.5 | AO69: CNP Sycamore | AP69: 44985 | AQ69: -28.2 | AR69: - Trip | AT69: Il Lusso | AU69: 44988 | AV69: -131.15 | AW69: - Trip | BD69: Caribou | BE69: 45068 | BF69: -14.78
A70: Walmart | B70: 44738 | C70: -14.86 | F70: The Crow (Work) | G70: 44749 | H70: -6.5 | P70: The Crow (Work) | Q70: 44814 | R70: -35 | U70: Aloft Hotel | V70: 44846 | W70: -20 | X70: - Florida | Z70: The Crow (Work) | AA70: 44894 | AB70: -37.93 | AE70: Buzzard Billy's | AF70: 44925 | AG70: -39 | AH70: - Night Out | AL70: =SUM(AL54:AL69) -> -455.26 | AQ70: =SUM(AQ55:AQ69) -> -279.96 | AT70: SQ Warhourse | AU70: 44989 | AV70: -36.5 | AW70: - Trip | AY70: Activities | AZ70: Date | BA70: Amount | BB70: Notes | BD70: Scooters Coffee | BE70: 45075 | BF70: -11.92
C71: =SUM(C66:C70) -> -61.62 | F71: Qdoba | G71: 44752 | H71: -22.76 | K71: Bars | L71: Date | M71: Amount | N71: Notes | P71: The Crow (Work) | Q71: 44815 | R71: -7.04 | U71: Auntie Anns | V71: 44847 | W71: -6.46 | X71: - Florida | AB71: =SUM(AB57:AB70) -> -153.81 | AE71: Animal House | AF71: 44925 | AG71: -26.14 | AH71: - Night Out | AT71: Madison Social | AU71: 44989 | AV71: -35.75 | AW71: - Trip | AY71: Forest Hills Golf | AZ71: 44993 | BA71: -17.94 | BF71: =SUM(BF53:BF70) -> -466.16
F72: The Crow (Work) | G72: 44756 | H72: -6.5 | K72: Week 1: | P72: Subway | Q72: 44817 | R72: -11.59 | U72: Rooster Puffs | V72: 44848 | W72: -32.23 | X72: - Florida | AE72: 4 Sisters Wine Bar | AF72: 44926 | AG72: -79.88 | AH72: - Night Out | AT72: Maple Street Biscuit | AU72: 44990 | AV72: -43.49 | AW72: - Trip | AY72: All Star Lanes | AZ72: 44994 | BA72: -10
F73: Qdoba | G73: 44757 | H73: -6.5 | K73: - Saturday | L73: 44779 | M73: -15 | P73: Caribou Coffee | Q73: 44817 | R73: -6.53 | U73: Brick House | V73: 44848 | W73: -55.48 | X73: - Florida | AG73: =SUM(AG53:AG72) -> -681.87 | AJ73: Bars | AK73: Date | AL73: Amount | AM73: Notes | AO73: Bars | AP73: Date | AQ73: Amount | AR73: Notes | AT73: Tailwind | AU73: 44992 | AV73: -17.82 | AW73: - Trip | AY73: Curb Caddy | AZ73: 45010 | BA73: -24
A74: Restuarants | B74: Date | C74: Amount | D74: Notes | F74: The Crow (Work) | G74: 44760 | H74: -6.32 | K74: Week 3: | P74: The Crow (Work) | Q74: 44820 | R74: -7.04 | U74: Sweetwater | V74: 44848 | W74: -3.12 | X74: - Florida | Z74: Bars | AA74: Date | AB74: Amount | AC74: Notes | AJ74: Week 1: | AO74: Week 1: | AT74: Caribou | AU74: 44994 | AV74: -7.75 | BA74: =SUM(BA71:BA73) -> -51.94 | BD74: Bars | BE74: Date | BF74: Amount | BG74: Notes
A75: The Root Note | B75: 44713 | C75: -20.4 | F75: Noodles and Company | G75: 44761 | H75: -33.6 | K75: - Thurs | L75: 44791 | M75: -4 | P75: The Crow (Work) | Q75: 44822 | R75: -6.5 | U75: Vale Food | V75: 44848 | W75: -14.49 | X75: - Florida | Z75: Week 1: | AE75: - Not Accurate | AJ75: - Wed-Fri | AK75: 44930 | AL75: -80 | AO75: - Thurs-Fri | AP75: 44959 | AQ75: -20 | AT75: The Crow | AU75: 44995 | AV75: -3.09 | BD75: Week 1-4:
A76: The Crow (Work) | B76: 44713 | C76: -6.5 | F76: The Crow (Work) | G76: 44762 | H76: -6.32 | K76: - Saturday | L76: 44793 | M76: -58.64 | P76: The Crow (Work) | Q76: 44823 | R76: -7.04 | U76: Aloft Hotel | V76: 44849 | W76: -21.5 | X76: - Florida | Z76: - Saturday | AA76: 44870 | AB76: -30 | AE76: Bars | AF76: Date | AG76: Amount | AH76: Notes | AJ76: Week 3: | AO76: Week 3: | AT76: The Crow | AU76: 44996 | AV76: -63.74 | BD76: - Thurs - Sat | BE76: 45047 | BF76: -120
A77: Subway | B77: 44715 | C77: -11.07 | F77: The Crow (Work) | G77: 44760 | H77: -6.5 | K77: Week 4: | P77: The Crow (Work) | Q77: 44825 | R77: -7.04 | U77: FL State Concessions | V77: 44849 | W77: -23.5 | X77: - Florida | Z77: Week 2: | AE77: Week 1-3 | AF77: 44898 | AG77: -100 | AJ77: - Thurs - Sat | AK77: 44945 | AL77: -40 | AO77: - Thurs - Sat | AP77: 44974 | AQ77: -55 | AR77: - Will's bday Weekend | AT77: The Crow | AU77: 44997 | AV77: -7.03 | AY77: Gifts | AZ77: Date | BA77: Amount | BB77: Notes
A78: Caribou Coffee | B78: 44719 | C78: -11.5 | D78: - Cash | F78: The Crow (Work) | G78: 44762 | H78: -6.5 | K78: - Saturday | L78: 44800 | M78: -35 | P78: Subway | Q78: 44826 | R78: -11.59 | U78: Chucks Fish | V78: 44849 | W78: -101.05 | X78: - Florida | Z78: - Saturday | AA78: 44877 | AB78: -30 | AE78: Week 4: | AJ78: Week 4: | AO78: Week 4: | AT78: Senior Villa | AU78: 44999 | AV78: -35.84 | BF78: =SUM(BF75:BF77) -> -120
A79: Caribou Coffee | B79: 44720 | C79: -6.95 | F79: Howies | G79: 44763 | H79: -27.33 | M79: =SUM(M72:M78) -> -112.64 | P79: The Crow (Work) | Q79: 44828 | R79: -24.36 | S79: - Drinks | U79: Madison Social | V79: 44850 | W79: -63.7 | X79: - Florida | Z79: Week 3: | AE79: - Wed-Sat | AF79: 44919 | AG79: 0 | AH79: - Recorded | AJ79: - Sat | AK79: 44954 | AL79: -30 | AO79: - Thurs - Sat | AP79: 44981 | AQ79: -20 | AT79: Top Shots | AU79: 45003 | AV79: -18.75
A80: The Charmont: Rooftop | B80: 44721 | C80: -51.77 | F80: The Crow (Work) | G80: 44768 | H80: -6.5 | P80: The Crow (Work) | Q80: 44828 | R80: -42.96 | U80: Aloft Hotel | V80: 44850 | W80: -3.23 | X80: - Florida | Z80: - Saturday | AA80: 44884 | AB80: -20 | AG80: =SUM(AG77:AG79) -> -100 | AL80: =SUM(AL74:AL79) -> -150 | AQ80: =SUM(AQ74:AQ79) -> -95 | AT80: Caribou | AU80: 45007 | AV80: -6.74 | BA80: =SUM(BA78:BA79) -> 0
A81: The Crow (Work) | B81: 44722 | C81: -6.5 | F81: Caribou Coffee | G81: 44769 | H81: -7.51 | P81: The Crow (Work) | Q81: 44829 | R81: -7.04 | U81: The Edison Restaurant | V81: 44851 | W81: -49 | X81: - Florida | AB81: =SUM(AB75:AB80) -> -80 | AT81: The Crow | AU81: 45007 | AV81: -26.86 | BD81: Activities | BE81: Date | BF81: Amount | BG81: Notes
A82: JavaVino | B82: 44723 | C82: -17.75 | F82: Qdoba | G82: 44770 | H82: 10.5 | K82: Activities | L82: Date | M82: Amount | N82: Notes | R82: =SUM(R62:R81) -> -239.69 | U82: Aloft Hotel | V82: 44850 | W82: -3.23 | X82: - Florida | AT82: Dels | AU82: 45008 | AV82: -43 | AW82: - Cash ATM | BD82: Pine Creek Golf Course | BE82: 45066 | BF82: -30
A83: Caribou Coffee | B83: 44725 | C83: -6.95 | F83: Culvers | G83: 44772 | H83: -21.08 | U83: Atlanta Conce | V83: 44852 | W83: -3.12 | X83: - Florida | AE83: Activities | AF83: Date | AG83: Amount | AH83: Notes | AJ83: Activities | AK83: Date | AL83: Amount | AM83: Notes | AO83: Activities | AP83: Date | AQ83: Amount | AR83: Notes | AT83: Caribou | AU83: 45008 | AV83: -7.75 | AY83: Other | AZ83: Date | BA83: Amount | BB83: Notes | BD83: Pine Creek Golf Course | BE83: 45066 | BF83: -9.5
A84: JavaVino | B84: 44726 | C84: -10 | F84: The Crow (Work) | G84: 44773 | H84: -6.5 | P84: Bars | Q84: Date | R84: Amount | S84: Notes | U84: Connection | V84: 44852 | W84: -5.48 | X84: - Florida | Z84: Activities | AA84: Date | AB84: Amount | AC84: Notes | AE84: Mt. La Crosse Ski | AF84: 44922 | AG84: -24 | AH84: - Lesson Lindsey | AJ84: Liquor for Trip | AK84: 44928 | AL84: -56.95 | AM84: - Trip Expense | AO84: Mt. La Crosse | AP84: 44961 | AQ84: -34 | AT84: Caribou | AU84: 45009 | AV84: -7.75 | AY84: Extra Expense | AZ84: 45023 | BA84: -12.63 | BD84: New Beginnings | BE84: 45068 | BF84: -27
A85: Culvers | B85: 44727 | C85: -12.86 | H85: =SUM(H67:H84) -> -195.72 | M85: =SUM(M83:M84) -> 0 | P85: Week 1: +Rides | Q85: 44806 | U85: Starbucks | V85: 44852 | W85: -7.58 | X85: - Florida | Z85: All Star Lanes | AA85: 44878 | AB85: -10 | AE85: Mt. La Crosse Ski | AF85: 44924 | AG85: -60 | AH85: - Lindsey & Friends | AO85: Mt. La Crosse | AP85: 44961 | AQ85: -24 | AT85: The Crow | AU85: 45009 | AV85: -53.88 | AY85: Extra Expense | AZ85: 45030 | BA85: -31.63
A86: The Crow (Work) | B86: 44722 | C86: -6.5 | P86: - Saturday | Q86: 44807 | R86: -20 | U86: Tailwind | V86: 44852 | W86: -4.29 | X86: - Florida | AB86: =SUM(AB85) -> -10 | AE86: Mt. La Crosse Ski | AF86: 44924 | AG86: -25 | AH86: - Drinks | AL86: =SUM(AL84:AL85) -> -56.95 | AO86: USPS | AP86: 44964 | AQ86: -17.9 | AR86: - Delivery Valentines | AT86: Twited Moose | AU86: 45010 | AV86: -9.36 | AW86: - Bar Night | AY86: Extra Expense | AZ86: 45045 | BA86: -10.54 | BF86: =SUM(BF82:BF85) -> -66.5
A87: The Crow (Work) | B87: 44729 | C87: -6.5 | P87: Week 2: +Rides | Q87: 44811 | U87: Caribou Coffee | V87: 44854 | W87: -7.51 | AE87: Mt. La Crosse Ski | AF87: 44924 | AG87: -14 | AH87: - Drinks | AO87: New Beginnings: Haircut | AP87: 44967 | AQ87: -27 | AT87: Caribou | AU87: 45013 | AV87: -7.75 | BA87: =SUM(BA84:BA86) -> -54.8
A88: Pettibone | B88: 44730 | C88: -31.83 | F88: Bars | G88: Date | H88: Amount | I88: Notes | K88: Gifts | L88: Date | M88: Amount | N88: Notes | P88: - Thursday | Q88: 44812 | R88: -40 | U88: The Crow (Work) | V88: 44855 | W88: -13.55 | AG88: =SUM(AG84:AG87) -> -123 | AO88: City of La Crosse | AP88: 44981 | AQ88: -21.5 | AT88: The Crow | AU88: 45013 | AV88: -7.58
A89: Caribou Coffee | B89: 44731 | C89: -11.5 | F89: Week 1: +Rides | P89: - Saturday | Q89: 44814 | R89: -40 | U89: The Crow (Work) | V89: 44856 | W89: -6.5 | Z89: Gifts | AA89: Date | AB89: Amount | AC89: Notes | AJ89: Gifts | AK89: Date | AL89: Amount | AM89: Notes | AQ89: =SUM(AQ84:AQ88) -> -124.4 | AV89: =SUM(AV62:AV88) -> -742.96 | BD89: Gifts | BE89: Date | BF89: Amount | BG89: Notes
A90: Caribou Coffee | B90: 44732 | C90: -14.26 | F90: - Saturday | G90: 44744 | H90: -50 | I90: - Zach in town | P90: Week 3: +Rides | Q90: 44818 | U90: Caribou Coffee | V90: 44861 | W90: -7.51 | AJ90: Elinor Flowers | AK90: 44957 | AL90: -89.16 | AY90: School | AZ90: Date | BA90: Amount | BB90: Notes | BD90: Venmo: Lindsey | BE90: 45070 | BF90: -100
A91: Mirage Sports Bar | B91: 44735 | C91: -10 | F91: Week 2: | M91: =SUM(M89:M90) -> 0 | P91: - Thursday | Q91: 44819 | R91: -22.46 | S91: - Card Transactions | U91: The Crow (Work) | V91: 44862 | W91: -7.04 | AE91: Gifts | AF91: Date | AG91: Amount | AH91: Notes | AJ91: Flight for Feb 28th | AK91: 44957 | AL91: -440.21
A92: The Crow (Work) | B92: 44736 | C92: -6.5 | F92: - Saturday | G92: 44751 | H92: -35 | P92: - Saturday | Q92: 44821 | R92: -40 | U92: The Crow (Work) | V92: 44864 | W92: -13.54 | AB92: =SUM(AB90:AB91) -> 0 | AL92: =SUM(AL90:AL91) -> -529.37 | AO92: Gifts | AP92: Date | AQ92: Amount | AR92: Notes | AT92: Bars | AU92: Date | AV92: Amount | AW92: Notes | BF92: =SUM(BF90:BF91) -> -100
A93: Buzzard Billy's | B93: 44737 | C93: -26.23 | F93: Week 3: | P93: Week 4: +Rides | Q93: 44827 | W93: =SUM(W63:W92) -> -557.12 | AO93: Starbucks: Lindsey | AP93: 44963 | AQ93: -18.6 | AT93: Week 1-4: | BA93: =SUM(BA91:BA92) -> 0
A94: Jules House Cafe | B94: 44738 | C94: -9.25 | F94: - Wednesday | G94: 44755 | H94: -33 | K94: Other | L94: Date | M94: Amount | N94: Notes | P94: - Saturday | Q94: 44828 | R94: -23 | AG94: =SUM(AG92:AG93) -> 0 | AQ94: =SUM(AQ93:AQ93) -> -18.6 | AT94: - Thurs-Fri | AU94: 44986 | AV94: -120
C95: =SUM(C75:C94) -> -284.82 | F95: Week 4: | K95: Extra Expense | L95: 44774 | M95: -110 | N95: 5 | P95: Week 5: | Q95: 44832 | Z95: Other | AA95: Date | AB95: Amount | AC95: Notes | AJ95: Other | AK95: Date | AL95: Amount | AM95: Notes | BD95: Other | BE95: Date | BF95: Amount | BG95: Notes
F96: - Wednesday | G96: 44755 | H96: -33 | K96: Extra Expense | L96: 44774 | M96: -22.99 | P96: - Thursday | Q96: 44833 | R96: -16 | U96: Bars | V96: Date | W96: Amount | X96: Notes | Z96: Extra Expense | AA96: 44866 | AB96: -200 | AC96: 5 | AJ96: Extra Expense | AK96: 44896 | AL96: -185 | AV96: =SUM(AV93:AV95) -> -120 | AY96: Reacurring Investments | AZ96: Date | BA96: Amount | BB96: Notes | BD96: Extra Expense | BE96: 45074 | BF96: -31.63
F97: Week 5: | K97: Extra Expense | L97: 44781 | M97: -22.67 | R97: =SUM(R85:R96) -> -201.46 | U97: Week 1: Rides | Z97: Extra Expense | AA97: 44868 | AB97: -22.67 | AE97: Christmas Gifts | AF97: Date | AG97: Amount | AH97: Notes | AJ97: Extra Expense | AK97: 44926 | AL97: -43 | AM97: - Florida Trip | AO97: Other | AP97: Date | AQ97: Amount | AR97: Notes | AY97: Acorns | AZ97: 45020 | BA97: -3
A98: Bars | B98: Date | C98: Amount | D98: Notes | F98: - Saturday | G98: 44755 | H98: -40 | I98: - After Mt. Olympus | K98: Extra Expense | L98: 44788 | M98: -22.67 | U98: - Thursday | V98: 44840 | W98: -15 | Z98: Extra Expense | AA98: 44875 | AB98: -22.67 | AE98: Skims (x6) | AF98: 44890 | AG98: -122.38 | AJ98: Extra Expense | AK98: 44928 | AL98: -35.83 | AO98: Extra Expense | AP98: 44960 | AQ98: -28.47 | AY98: Acorns | AZ98: 45020 | BA98: -6 | BF98: =SUM(BF96:BF97) -> -31.63
A99: Week 1 | H99: =SUM(H89:H98) -> -191 | K99: Extra Expense | L99: 44794 | M99: -22.67 | U99: - Friday | V99: 44841 | W99: -15 | Z99: Extra Expense | AA99: 44881 | AB99: -22.67 | AE99: Lonely Ghost (x1) | AF99: 44891 | AG99: -48.08 | AJ99: Extra Expense | AK99: 44932 | AL99: -24.71 | AO99: Extra Expense | AP99: 44967 | AQ99: -56.95 | AT99: Activities | AU99: Date | AV99: Amount | AW99: Notes | AY99: Acorns | AZ99: 45021 | BA99: -5
A100: - Friday | B100: 44715 | C100: -26 | K100: Extra Expense | L100: 44800 | M100: 0 | N100: - Dad Paid | P100: Activities | Q100: Date | R100: Amount | S100: Notes | U100: - Saturday | V100: 44842 | W100: -40 | Z100: Extra Expense | AA100: 44888 | AB100: -22.67 | AE100: Lonely Ghost (x2) | AF100: 44892 | AG100: -71.75 | AJ100: Extra Expense | AK100: 44935 | AL100: -21.49 | AO100: Extra Expense | AP100: 44968 | AQ100: -8.43 | AR100: - Dad | AT100: Curb Caddy | AU100: 44989 | AV100: -24 | AW100: - Trip | AY100: Coinbase | AZ100: 45023 | BA100: -10
A101: - Ssturday | B101: 44716 | C101: -26 | M101: =SUM(M95:M100) -> -201 | P101: Haircut | Q101: 44832 | R101: -27 | U101: Week 2: Rides | Z101: Extra Expense | AA101: 44894 | AB101: -22.67 | AE101: Etsy (x2) | AF101: 44894 | AG101: -59.08 | AJ101: Extra Expense | AK101: 44938 | AL101: -24.71 | AO101: Extra Expense | AP101: 44978 | AQ101: -44.32 | AR101: - Switched Salt Nic | AT101: All Star Lanes | AU101: 44997 | AV101: -23 | AY101: Acorns | AZ101: 45026 | BA101: -6.44 | BD101: School | BE101: Date | BF101: Amount | BG101: Notes
A102: Week 2 | F102: Activities | G102: Date | H102: Amount | I102: Notes | U102: - Saturday | V102: 44849 | W102: -20 | AB102: =SUM(AB96:AB101) -> -313.35 | AE102: Custom Man | AF102: 44895 | AG102: -55.99 | AJ102: Extra Expense | AK102: 44946 | AL102: -22.67 | AO102: Extra Expense | AP102: 44985 | AQ102: -10.54 | AR102: - Tests | AT102: All Star Lanes | AU102: 44997 | AV102: -10 | AY102: Acorns | AZ102: 45028 | BA102: -5
A103: - Saturday | B103: 44723 | C103: -28 | F103: Forest Hills Golf | G103: 44744 | H103: -33.78 | R103: =SUM(R101:R102) -> -27 | U103: Week 3: Rides | AE103: Lonely Ghost (x1) | AF103: 44899 | AG103: -169.48 | AJ103: Extra Expense | AK103: 44952 | AL103: -28.46 | AQ103: =SUM(AQ98:AQ102) -> -148.71 | AT103: YMCA | AU103: 45000 | AV103: -10 | AY103: Coinbase | AZ103: 45030 | BA103: -10
...

Sheet Work Hours 
A1: Fincancial Portfolio: Work Data
A2: Work Hours
A4: The Crow
A5: Month 1: June
A6: Work Dates: Daw | B6: Hours | C6: Wage Pay | D6: Notes
A7: Daw Mowing
A8: - 6/8/2022 | B8: 2 | C8: 40
A9: - Extra | C9: 25
C10: =SUM(C6:C9) -> 65
A12: 2022-23 | C12: $10 /hour | K12: 2023-24 | U12: Trust Point: Intern
A13: Month 1: June 2022 | C13: $8.50 /hour | K13: Month 1: June 2023 | M13: $8.50 /hour | U13: Month 1: March | W13: $14.00 /hour
A14: Work Dates: The Crow | B14: Hours | C14: Wage Pay | D14: Tips | E14: Tip Outs | F14: Avg Wage/Hour | G14: Total | H14: Notes | K14: Work Dates: The Crow | L14: Hours | M14: Wage Pay | N14: Tips | O14: Tip Outs | P14: Avg Wage/Hour | Q14: Total | R14: Notes | U14: Work Dates: | V14: Hours | W14: Wage Pay
A15: Week 43: 5/30 - 6/5 | K15: Week 95: 5/29 - 6/4 | U15: Week 1: 3/27 - 4/2
A16: - Mon 5/30 | B16: 6 | C16: =B16*8.5 -> 51 | D16: 45 | F16: =(C16+D16)/B16 -> 16 | G16: =C16+D16 -> 96 | K16: - Mon 5/29 | L16: 7.5 | M16: =L16*5 -> 37.5 | N16: 120 | P16: =(M16+N16)/L16 -> 21 | Q16: =M16+N16 -> 157.5 | U16: - Mon 3/27 | V16: 3.5 | W16: =V16*14 -> 49
A17: - Wed 6/1 | B17: 6 | C17: =B17*8.5 -> 51 | D17: 33 | F17: =(C17+D17)/B17 -> 14 | G17: =C17+D17 -> 84 | K17: - Tues 5/30 | L17: 6.5 | M17: =L17*5 -> 32.5 | N17: 88 | P17: =(M17+N17)/L17 -> 18.538462 | Q17: =M17+N17 -> 120.5 | U17: - Fri 3/31 | V17: 5 | W17: =V17*14 -> 70
A18: - Thurs 6/2 | B18: 6.5 | C18: =B18*14.5 -> 94.25 | D18: 47 | F18: =(C18+D18)/B18 -> 21.730769 | G18: =C18+D18 -> 141.25 | H18: - Dishwashed+Tips | K18: - Wed 5/31 | L18: 6 | M18: =L18*5 -> 30 | N18: 74 | P18: =(M18+N18)/L18 -> 17.333333 | Q18: =M18+N18 -> 104 | V18: =SUM(V16:V17) -> 8.5 | W18: =SUM(W16:W17) -> 119
B19: =SUM(B15:B18) -> 18.5 | C19: =SUM(C15:C18) -> 196.25 | D19: =SUM(D15:D18) -> 125 | E19: =SUM(E15:E18) -> 0 | F19: =(C19+D19)/B19 -> 17.364865 | G19: =C19+D19 -> 321.25 | K19: - Fri 6/2 | L19: 7.5 | M19: =L19*15 -> 112.5 | P19: =(M19+N19)/L19 -> 15 | Q19: =M19+N19 -> 112.5
A20: Week 44: 6/6 - 6/12 | K20: - Sun 6/4 | L20: 8.5 | M20: =(3.5*5)+(5*15) -> 92.5 | N20: 16 | P20: =(M20+N20)/L20 -> 12.764706 | Q20: =M20+N20 -> 108.5 | R20: - Double | U20: Total | V20: =V18 -> 8.5 | W20: =W18 -> 119
A21: - Tues 6/7 | B21: 6 | C21: =B21*8.5 -> 51 | D21: 53 | F21: =(C21+D21)/B21 -> 17.333333 | G21: =C21+D21 -> 104 | L21: =SUM(L15:L20) -> 36 | M21: =SUM(M15:M20) -> 305 | N21: =SUM(N15:N20) -> 298 | O21: =SUM(O15:O20) -> 0 | P21: =(M21+N21)/L21 -> 16.75 | Q21: =M21+N21 -> 603
A22: - Wed 6/8 | B22: 6.5 | C22: =B22*8.5 -> 55.25 | D22: 33 | F22: =(C22+D22)/B22 -> 13.576923 | G22: =C22+D22 -> 88.25 | H22: - Raise!! = $10/hour | K22: Week 96: 6/5 - 6/11
A23: - Fri 6/10 | B23: 7.5 | C23: =B23*8.5 -> 63.75 | D23: 67 | F23: =(C23+D23)/B23 -> 17.433333 | G23: =C23+D23 -> 130.75 | K23: - Wed 6/7 | L23: 6 | M23: =L23*5 -> 30 | N23: 119 | O23: 165 | P23: =(M23+N23)/L23 -> 24.833333 | Q23: =M23+N23 -> 149 | U23: Month 2: April | W23: $14.00 /hour
A24: - Sun 6/12 | B24: 4.5 | C24: =B24*8.5 -> 38.25 | D24: 24 | E24: 239 | F24: =(C24+D24)/B24 -> 13.833333 | G24: =C24+D24 -> 62.25 | H24: - Close Early, Meeting, Tip Out | K24: - Thurs 6/8 | L24: 5.5 | M24: =L24*15 -> 82.5 | P24: =(M24+N24)/L24 -> 15 | Q24: =M24+N24 -> 82.5 | U24: Work Dates: | V24: Hours | W24: Wage Pay
B25: =SUM(B21:B24) -> 24.5 | C25: =SUM(C21:C24) -> 208.25 | D25: =SUM(D21:D24) -> 177 | E25: =SUM(E21:E24) -> 239 | F25: =(C25+D25)/B25 -> 15.72449 | G25: =C25+D25 -> 385.25 | H25: 624.25 | K25: - Fri 6/9 | L25: 7 | M25: =L25*10 -> 70 | N25: 64 | P25: =(M25+N25)/L25 -> 19.142857 | Q25: =M25+N25 -> 134 | U25: Week 2: 4/3 - 4/9
A26: Week 45: 6/13 - 6/19 - Raise | K26: - Sun 6/11 | L26: 5.5 | M26: =L26*10 -> 55 | N26: 54 | P26: =(M26+N26)/L26 -> 19.818182 | Q26: =M26+N26 -> 109 | U26: - Mon 4/3 | V26: 1 | W26: =V26*14 -> 14
A27: - Tues 6/14 | B27: 6 | C27: =B27*10 -> 60 | D27: 56 | F27: =(C27+D27)/B27 -> 19.333333 | G27: =C27+D27 -> 116 | H27: - Paid: Start of Raise only $9.50 | L27: =SUM(L22:L26) -> 24 | M27: =SUM(M22:M26) -> 237.5 | N27: =SUM(N22:N26) -> 237 | O27: =SUM(O22:O26) -> 165 | P27: =(M27+N27)/L27 -> 19.770833 | Q27: =M27+N27 -> 474.5 | V27: =SUM(V26:V26) -> 1 | W27: =SUM(W26:W26) -> 14
A28: - Thurs 6/16 | B28: 5.5 | C28: =B28*14.5 -> 79.75 | D28: 0 | F28: =(C28+D28)/B28 -> 14.5 | G28: =C28+D28 -> 79.75 | K28: Week 97: 6/12 - 6/18
A29: - Fri 6/17 | B29: 6.5 | C29: =B29*10 -> 65 | D29: 49 | F29: =(C29+D29)/B29 -> 17.538462 | G29: =C29+D29 -> 114 | K29: - Wed 6/14 | L29: 5.5 | M29: =L29*15 -> 82.5 | P29: =(M29+N29)/L29 -> 15 | Q29: =M29+N29 -> 82.5 | U29: Total | V29: =V27 -> 1 | W29: =W27 -> 14
A30: - Sun 6/19 | B30: 4 | C30: =B30*10 -> 40 | D30: 33 | F30: =(C30+D30)/B30 -> 18.25 | G30: =C30+D30 -> 73 | K30: - Thurs 6/15 | L30: 7.5 | M30: =L30*5 -> 37.5 | N30: 118 | P30: =(M30+N30)/L30 -> 20.733333 | Q30: =M30+N30 -> 155.5
B31: =SUM(B27:B30) -> 22 | C31: =SUM(C27:C30) -> 244.75 | D31: =SUM(D27:D30) -> 138 | E31: =SUM(E27:E30) -> 0 | F31: =(C31+D31)/B31 -> 17.397727 | G31: =C31+D31 -> 382.75 | K31: - Fri 6/16 | L31: 5.5 | M31: =L31*10 -> 55 | N31: 41 | P31: =(M31+N31)/L31 -> 17.454545 | Q31: =M31+N31 -> 96
A32: Week 46: 6/20 - 6/26 | K32: - Sun 6/18 | L32: 6 | M32: =L32*15 -> 90 | P32: =(M32+N32)/L32 -> 15 | Q32: =M32+N32 -> 90
A33: - Tues 6/21 | B33: 6 | C33: =B33*10 -> 60 | D33: 51 | F33: =(C33+D33)/B33 -> 18.5 | G33: =C33+D33 -> 111 | H33: - Paid | L33: =SUM(L28:L32) -> 24.5 | M33: =SUM(M28:M32) -> 265 | N33: =SUM(N28:N32) -> 159 | O33: =SUM(O28:O32) -> 0 | P33: =(M33+N33)/L33 -> 17.306122 | Q33: =M33+N33 -> 424
A34: - Thurs 6/23 | B34: 6.5 | C34: =B34*10 -> 65 | D34: 60 | F34: =(C34+D34)/B34 -> 19.230769 | G34: =C34+D34 -> 125 | K34: Week 98: 6/19 - 6/25
A35: - Fri 6/24 | B35: 6.5 | C35: =B35*10 -> 65 | D35: 38 | F35: =(C35+D35)/B35 -> 15.846154 | G35: =C35+D35 -> 103 | K35: - Wed 6/22 | L35: 8 | M35: =L35*5 -> 40 | N35: 122 | P35: =(M35+N35)/L35 -> 20.25 | Q35: =M35+N35 -> 162
B36: =SUM(B33:B35) -> 19 | C36: =SUM(C33:C35) -> 190 | D36: =SUM(D33:D35) -> 149 | E36: =SUM(E33:E35) -> 0 | F36: =(C36+D36)/B36 -> 17.842105 | G36: =C36+D36 -> 339 | K36: - Thurs 6/23 | L36: 9 | M36: =L36*5 -> 45 | N36: 88 | O36: 94 | P36: =(M36+N36)/L36 -> 14.777778 | Q36: =M36+N36 -> 133
K37: - Sun 6/8 | L37: 2.5 | M37: =L37*7.5 -> 18.75 | P37: =(M37+N37)/L37 -> 7.5 | Q37: =M37+N37 -> 18.75 | R37: - Meeting
A38: Total | B38: =B19+B25+B31+B36 -> 84 | C38: =C19+C25+C31+C36 -> 839.25 | D38: =D19+D25+D31+D36 -> 589 | E38: =E19+E25+E31+E36 -> 239 | F38: =(C38+D38+E38)/B38 -> 19.848214 | G38: =C38+D38+E38 -> 1667.25 | L38: =SUM(L35:L37) -> 19.5 | M38: =SUM(M35:M37) -> 103.75 | N38: =SUM(N35:N37) -> 210 | O38: =SUM(O35:O37) -> 94 | P38: =(M38+N38)/L38 -> 16.089744 | Q38: =M38+N38 -> 313.75
K39: Week 99: 6/26 - 7/2
K40: - Mon 6/26 | L40: 5.5 | M40: =L40*15 -> 82.5 | P40: =(M40+N40)/L40 -> 15 | Q40: =M40+N40 -> 82.5 | R40: - Paid
A41: Month 2: July 2022 | K41: - Thurs 6/29 | L41: 8.5 | M41: =L41*5 -> 42.5 | N41: 108 | P41: =(M41+N41)/L41 -> 17.705882 | Q41: =M41+N41 -> 150.5
A42: Work Dates: Daw | B42: Hours | C42: Wage Pay | D42: Notes | K42: - Fri 6/30 | L42: 7 | M42: =L42*15 -> 105 | O42: 75 | P42: =(M42+N42)/L42 -> 15 | Q42: =M42+N42 -> 105 | R42: Tip Out
A43: Daw Mowing | K43: - Sun 7/2 | L43: 8 | M43: =L43*5 -> 40 | N43: 63 | P43: =(M43+N43)/L43 -> 12.875 | Q43: =M43+N43 -> 103
A44: - 7/12/2022 | B44: 1.5 | C44: 35 | D44: - Not Paid | L44: =SUM(L40:L43) -> 29 | M44: =SUM(M40:M43) -> 270 | N44: =SUM(N40:N43) -> 171 | O44: =SUM(O40:O43) -> 75 | P44: =(M44+N44)/L44 -> 15.206897 | Q44: =M44+N44 -> 441
C45: =SUM(C41:C44) -> 35
K46: Total | L46: =L21+L27+L33+L38+L44 -> 133 | M46: =M21+M27+M33+M38+M44 -> 1181.25 | N46: =N21+N27+N33+N38+N44 -> 1075 | O46: =O21+O27+O33+O38+O44 -> 334 | P46: =(M46+N46+O46)/L46 -> 19.475564 | Q46: =M46+N46+O46 -> 2590.25
A47: Month 2: July | C47: $10 /hour
A48: Work Dates: The Crow | B48: Hours | C48: Wage Pay | D48: Tips | E48: Tip Outs | F48: Avg Wage/Hour | G48: Total | H48: Notes
A49: Week 47: 6/27 - 7/3 | K49: Month 2: July 2023
A50: - Wed 6/29 | B50: 6.5 | C50: =B50*10 -> 65 | D50: 45 | F50: =(C50+D50)/B50 -> 16.923077 | G50: =C50+D50 -> 110 | H50: - Paid for (6/6 - 6/19) | K50: Work Dates: The Crow | L50: Hours | M50: Wage Pay | N50: Tips | O50: Tip Outs | P50: Avg Wage/Hour | Q50: Total | R50: Notes
A51: - Thur 6/30 | B51: 6 | C51: =B51*10 -> 60 | D51: 29 | F51: =(C51+D51)/B51 -> 14.833333 | G51: =C51+D51 -> 89 | K51: Week 100: 7/3 - 7/9
A52: - Fri 7/1 | B52: 6.5 | C52: =B52*10 -> 65 | D52: 29 | F52: =(C52+D52)/B52 -> 14.461538 | G52: =C52+D52 -> 94 | K52: - Mon 7/3 | L52: 9 | M52: =L52*5 -> 45 | N52: 178 | P52: =(M52+N52)/L52 -> 24.777778 | Q52: =M52+N52 -> 223
A53: - Sun 7/3 | B53: 7.5 | C53: =B53*10 -> 75 | D53: 87 | E53: 212 | F53: =(C53+D53)/B53 -> 21.6 | G53: =C53+D53 -> 162 | H53: Tip out collected w/o Sun tip out | K53: - Tues 7/4 | L53: 7.5 | M53: =L53*5 -> 37.5 | N53: 163 | P53: =(M53+N53)/L53 -> 26.733333 | Q53: =M53+N53 -> 200.5 | R53: - 4th of July, Morning shift
B54: =SUM(B50:B53) -> 26.5 | C54: =SUM(C50:C53) -> 265 | D54: =SUM(D50:D53) -> 190 | E54: =SUM(E50:E53) -> 212 | F54: =(C54+D54)/B54 -> 17.169811 | G54: =C54+D54 -> 455 | K54: - Wed 7/5 | L54: 8.5 | M54: =L54*5 -> 42.5 | N54: 129 | P54: =(M54+N54)/L54 -> 20.176471 | Q54: =M54+N54 -> 171.5
A55: Week 48: 7/4 - 7/10 | K55: - Sun 7/9 | L55: 6 | M55: =L55*10 -> 60 | N55: 41 | O55: 114 | P55: =(M55+N55)/L55 -> 16.833333 | Q55: =M55+N55 -> 101 | R55: - Collected Tip Outs
A56: - Mon 7/4 | B56: 6 | C56: =B56*15 -> 90 | D56: 0 | F56: =(C56+D56)/B56 -> 15 | G56: =C56+D56 -> 90 | H56: - 4th of July | L56: =SUM(L51:L55) -> 31 | M56: =SUM(M51:M55) -> 185 | N56: =SUM(N51:N55) -> 511 | O56: =SUM(O51:O55) -> 114 | P56: =(M56+N56+O56)/L56 -> 26.129032 | Q56: =M56+N56 -> 696
A57: - Tues 7/5 | B57: 5 | C57: =B57*10 -> 50 | D57: 36 | F57: =(C57+D57)/B57 -> 17.2 | G57: =C57+D57 -> 86 | K57: Week 101: 7/10 - 7/16
A58: - Wed 7/6 | B58: 5 | C58: =B58*15 -> 75 | D58: 0 | F58: =(C58+D58)/B58 -> 15 | G58: =C58+D58 -> 75 | H58: - Hours? | K58: - Thurs 7/10 | L58: 5.5 | M58: =L58*15 -> 82.5 | P58: =(M58+N58)/L58 -> 15 | Q58: =M58+N58 -> 82.5
A59: - Thur 7/7 | B59: 6 | C59: =B59*10 -> 60 | D59: 36 | F59: =(C59+D59)/B59 -> 16 | G59: =C59+D59 -> 96 | K59: - Sun 7/16 | L59: 5.5 | M59: =L59*15 -> 82.5 | P59: =(M59+N59)/L59 -> 15 | Q59: =M59+N59 -> 82.5
A60: - Fri 7/8 | B60: 6.5 | C60: =B60*10 -> 65 | D60: 53 | F60: =(C60+D60)/B60 -> 18.153846 | G60: =C60+D60 -> 118 | L60: =SUM(L57:L59) -> 11 | M60: =SUM(M57:M59) -> 165 | N60: =SUM(N57:N59) -> 0 | O60: =SUM(O57:O59) -> 0 | P60: =(M60+N60+O60)/L60 -> 15 | Q60: =M60+N60 -> 165
A61: - Sun 7/10 | B61: 1.5 | C61: =B61*10 -> 15 | D61: 0 | F61: =(C61+D61)/B61 -> 10 | G61: =C61+D61 -> 15 | K61: Week 102: 7/17 - 7/23
B62: =SUM(B56:B61) -> 30 | C62: =SUM(C56:C61) -> 355 | D62: =SUM(D56:D61) -> 125 | E62: =SUM(E56:E61) -> 0 | F62: =(C62+D62)/B62 -> 16 | G62: =C62+D62 -> 480 | K62: - Wed 7/19 | L62: 7 | M62: =L62*5 -> 35 | N62: 70 | P62: =(M62+N62)/L62 -> 15 | Q62: =M62+N62 -> 105
A63: Week 49: 7/11 - 7/17 | K63: - Thurs 7/20 | L63: 9 | M63: =L63*5 -> 45 | N63: 120 | O63: 79 | P63: =(M63+N63)/L63 -> 18.333333 | Q63: =M63+N63 -> 165
A64: - Mon 7/11 | B64: 5.5 | C64: =B64*15 -> 82.5 | D64: 0 | F64: =(C64+D64)/B64 -> 15 | G64: =C64+D64 -> 82.5 | L64: =SUM(L61:L63) -> 16 | M64: =SUM(M61:M63) -> 80 | N64: =SUM(N61:N63) -> 190 | O64: =SUM(O61:O63) -> 79 | P64: =(M64+N64+O64)/L64 -> 21.8125 | Q64: =M64+N64 -> 270
A65: - Tues 7/12 | B65: 7.5 | C65: =B65*10 -> 75 | D65: 68 | F65: =(C65+D65)/B65 -> 19.066667 | G65: =C65+D65 -> 143 | H65: - Paid For (6/20 - 7/3) | K65: Week 103: 7/24 - 7/30
A66: - Thur 7/14 | B66: 6 | C66: =B66*10 -> 60 | D66: 28 | F66: =(C66+D66)/B66 -> 14.666667 | G66: =C66+D66 -> 88 | K66: - Thurs 7/10 | L66: 7.5 | M66: =L66*5 -> 37.5 | N66: 117 | P66: =(M66+N66)/L66 -> 20.6 | Q66: =M66+N66 -> 154.5
A67: - Fri 7/15 | B67: 6.5 | C67: =B67*10 -> 65 | D67: 50 | F67: =(C67+D67)/B67 -> 17.692308 | G67: =C67+D67 -> 115 | K67: - Sun 7/16 | L67: 6.5 | M67: =L67*5 -> 32.5 | N67: 71 | O67: 75 | P67: =(M67+N67)/L67 -> 15.923077 | Q67: =M67+N67 -> 103.5
A68: - Sun 7/17 | B68: 5.5 | C68: =B68*15 -> 82.5 | D68: 0 | F68: =(C68+D68)/B68 -> 15 | G68: =C68+D68 -> 82.5 | L68: =SUM(L65:L67) -> 14 | M68: =SUM(M65:M67) -> 70 | N68: =SUM(N65:N67) -> 188 | O68: =SUM(O65:O67) -> 75 | P68: =(M68+N68+O68)/L68 -> 23.785714 | Q68: =M68+N68 -> 258
B69: =SUM(B64:B68) -> 31 | C69: =SUM(C64:C68) -> 365 | D69: =SUM(D64:D68) -> 146 | E69: =SUM(E64:E68) -> 0 | F69: =(C69+D69)/B69 -> 16.483871 | G69: =C69+D69 -> 511
A70: Week 50: 7/18 - 7/24 | K70: Total | L70: =L56+L60+L64+L68 -> 72 | M70: =M56+M60+M64+M68 -> 500 | N70: =N56+N60+N64+N68 -> 889 | O70: =O56+O60+O64+O68 -> 268 | P70: =(M70+N70+O70)/L70 -> 23.013889 | Q70: =M70+N70+O70 -> 1657
A71: - Mon 7/18 | B71: 5.5 | C71: =B71*15 -> 82.5 | D71: 0 | F71: =(C71+D71)/B71 -> 15 | G71: =C71+D71 -> 82.5 | H71: - Moved to $15/hour - Dishwash
A72: - Wed 7/20 | B72: 6.5 | C72: =B72*10 -> 65 | D72: 44 | F72: =(C72+D72)/B72 -> 16.769231 | G72: =C72+D72 -> 109
A73: - Thur 7/22 | B73: 6.5 | C73: =B73*10 -> 65 | D73: 23 | F73: =(C73+D73)/B73 -> 13.538462 | G73: =C73+D73 -> 88 | K73: Month 3: August 2023
A74: - Sun 7/24 | B74: 5.5 | C74: =B74*15 -> 82.5 | D74: 0 | E74: 220 | F74: =(C74+D74)/B74 -> 15 | G74: =C74+D74 -> 82.5 | H74: - Tip Outs | K74: Work Dates: The Crow | L74: Hours | M74: Wage Pay | N74: Tips | O74: Tip Outs | P74: Avg Wage/Hour | Q74: Total | R74: Notes
B75: =SUM(B70:B74) -> 24 | C75: =SUM(C70:C74) -> 295 | D75: =SUM(D70:D74) -> 67 | E75: =SUM(E70:E74) -> 220 | F75: =(C75+D75)/B75 -> 15.083333 | G75: =C75+D75 -> 362 | K75: Week 104: 7/31 - 8/6
A76: Week 51: 7/25 - 7/31 | K76: - Mon 7/31 | L76: 8 | M76: =L76*5 -> 40 | N76: 132 | P76: =(M76+N76)/L76 -> 21.5 | Q76: =M76+N76 -> 172
A77: - Mon 7/25 | B77: 4.5 | C77: =B77*15 -> 67.5 | D77: 0 | F77: =(C77+D77)/B77 -> 15 | G77: =C77+D77 -> 67.5 | K77: - Tues 8/1 | L77: 8.5 | M77: =L77*5 -> 42.5 | N77: 96 | P77: =(M77+N77)/L77 -> 16.294118 | Q77: =M77+N77 -> 138.5 | R77: - Trainee Tonight
A78: - Tues 7/26 | B78: 5.5 | C78: =B78*10 -> 55 | D78: 27 | F78: =(C78+D78)/B78 -> 14.909091 | G78: =C78+D78 -> 82 | H78: - Paid For (7/4 - 7/17) | K78: - Wed 8/2 | L78: 8 | M78: =L78*5 -> 40 | N78: 73 | P78: =(M78+N78)/L78 -> 14.125 | Q78: =M78+N78 -> 113 | R78: - Bar Lead coming soon!
A79: - Thur 7/28 | B79: 5 | C79: =B79*15 -> 75 | D79: 0 | F79: =(C79+D79)/B79 -> 15 | G79: =C79+D79 -> 75 | L79: =SUM(L75:L78) -> 24.5 | M79: =SUM(M75:M78) -> 122.5 | N79: =SUM(N75:N78) -> 301 | O79: =SUM(O75:O78) -> 0 | P79: =(M79+N79+O79)/L79 -> 17.285714 | Q79: =M79+N79 -> 423.5
A80: - Fri 7/29 | B80: 7.5 | C80: =B80*10 -> 75 | D80: 77 | F80: =(C80+D80)/B80 -> 20.266667 | G80: =C80+D80 -> 152 | K80: Week 105: 8/7 - 8/13
A81: - Sun 7/31 | B81: 5.5 | C81: =B81*10 -> 55 | D81: 21 | F81: =(C81+D81)/B81 -> 13.818182 | G81: =C81+D81 -> 76 | K81: - Mon 8/7 | L81: 7.5 | M81: =L81*5 -> 37.5 | N81: 141 | O81: 127 | P81: =(M81+N81)/L81 -> 23.8 | Q81: =M81+N81 -> 178.5
B82: =SUM(B76:B81) -> 28 | C82: =SUM(C76:C81) -> 327.5 | D82: =SUM(D76:D81) -> 125 | E82: =SUM(E76:E81) -> 0 | F82: =(C82+D82)/B82 -> 16.160714 | G82: =C82+D82 -> 452.5 | K82: - Tues 8/8 | L82: 8.5 | M82: =L82*5 -> 42.5 | N82: 133 | P82: =(M82+N82)/L82 -> 20.647059 | Q82: =M82+N82 -> 175.5 | R82: - Paid
K83: - Wed 8/9 | L83: 6 | M83: =L83*15 -> 90 | P83: =(M83+N83)/L83 -> 15 | Q83: =M83+N83 -> 90
K84: - Sun 8/13 | L84: 7.5 | M84: =L84*5 -> 37.5 | N84: 107 | P84: =(M84+N84)/L84 -> 19.266667 | Q84: =M84+N84 -> 144.5
A85: Total | B85: =B54+B62+B69+B75+B82 -> 139.5 | C85: =C54+C62+C69+C75+C82 -> 1607.5 | D85: =D54+D62+D69+D75+D82 -> 653 | E85: =E54+E62+E69+E75+E82 -> 432 | F85: =(C85+D85+E85)/B85 -> 19.301075 | G85: =C85+D85+E85 -> 2692.5 | L85: =SUM(L81:L84) -> 29.5 | M85: =SUM(M81:M84) -> 207.5 | N85: =SUM(N81:N84) -> 381 | O85: =SUM(O81:O84) -> 127 | P85: =(M85+N85+O85)/L85 -> 24.254237 | Q85: =M85+N85 -> 588.5
K86: Week 106: 8/14 - 8/20
K87: - Tues 8/15 | L87: 6.5 | M87: =L87*10 -> 65 | N87: 65 | O87: 102 | P87: =(M87+N87)/L87 -> 20 | Q87: =M87+N87 -> 130
A88: Month 3: August 2022 | K88: - Wed 8/16 | L88: 7.5 | M88: =L88*7.25 -> 54.375 | N88: 112 | P88: =(M88+N88)/L88 -> 22.183333 | Q88: =M88+N88 -> 166.375 | R88: - Officially Bar Lead!!
A89: Work Dates: Daw | B89: Hours | C89: Wage Pay | D89: Notes | K89: - Thurs 8/17 | L89: 5.5 | M89: =L89*15 -> 82.5 | P89: =(M89+N89)/L89 -> 15 | Q89: =M89+N89 -> 82.5 | R89: - Raise $7.25
A90: Daw Mowing | K90: - Sun 8/20 | L90: 7 | M90: =L90*7.25 -> 50.75 | N90: 56 | P90: =(M90+N90)/L90 -> 15.25 | Q90: =M90+N90 -> 106.75
A91: - | L91: =SUM(L87:L90) -> 26.5 | M91: =SUM(M87:M90) -> 252.625 | N91: =SUM(N87:N90) -> 233 | O91: =SUM(O87:O90) -> 102 | P91: =(M91+N91+O91)/L91 -> 22.174528 | Q91: =M91+N91 -> 485.625
C92: =SUM(C88:C91) -> 0 | K92: Week 107: 8/21 - 8/27
K93: - Week Off | L93: 1 | M93: =L93*10 -> 10 | N93: 0 | P93: =(M93+N93)/L93 -> 10 | Q93: =M93+N93 -> 10 | R93: - Paid
A94: Month 3: August | C94: $10 /hour | L94: =SUM(L93) -> 1 | M94: =SUM(M93) -> 10 | N94: =SUM(N93) -> 0 | O94: =SUM(O93) -> 0 | P94: =(M94+N94+O94)/L94 -> 10 | Q94: =M94+N94 -> 10
A95: Work Dates: The Crow | B95: Hours | C95: Wage Pay | D95: Tips | E95: Tip Outs | F95: Avg Wage/Hour | G95: Total | H95: Notes | K95: Week 108: 8/28 - 9/3
A96: Week 52: 8/1 - 7/7 | K96: - Mon 8/28 | L96: 8.5 | M96: =L96*7.25 -> 61.625 | N96: 78 | P96: =(M96+N96)/L96 -> 16.426471 | Q96: =M96+N96 -> 139.625
A97: - Tues 8/2 | B97: 6.5 | C97: =B97*10 -> 65 | D97: 42 | F97: =(C97+D97)/B97 -> 16.461538 | G97: =C97+D97 -> 107 | K97: - Tues 8/29 | L97: 6 | M97: =L97*15 -> 90 | P97: =(M97+N97)/L97 -> 15 | Q97: =M97+N97 -> 90
A98: - Wed 8/3 | B98: 7 | C98: =B98*10 -> 70 | D98: 75 | F98: =(C98+D98)/B98 -> 20.714286 | G98: =C98+D98 -> 145 | K98: - Wed 8/30 | L98: 8 | M98: =L98*7.25 -> 58 | N98: 110 | P98: =(M98+N98)/L98 -> 21 | Q98: =M98+N98 -> 168
A99: - Thur 8/4 | B99: 5.5 | C99: =B99*15 -> 82.5 | D99: 0 | F99: =(C99+D99)/B99 -> 15 | G99: =C99+D99 -> 82.5 | K99: - Thurs 8/31 | L99: 7.5 | M99: =L99*7.25 -> 54.375 | N99: 105 | P99: =(M99+N99)/L99 -> 21.25 | Q99: =M99+N99 -> 159.375
A100: - Fri 8/5 | B100: 6 | C100: =B100*15 -> 90 | D100: 0 | F100: =(C100+D100)/B100 -> 15 | G100: =C100+D100 -> 90 | K100: - Fri 9/1 | L100: 8 | M100: =L100*15 -> 120 | P100: =(M100+N100)/L100 -> 15 | Q100: =M100+N100 -> 120
A101: - Sun 7/7 | B101: 4.5 | C101: =B101*10 -> 45 | D101: 24 | F101: =(C101+D101)/B101 -> 15.333333 | G101: =C101+D101 -> 69 | K101: - Sat 9/2 | L101: 5.5 | M101: =L101*15 -> 82.5 | P101: =(M101+N101)/L101 -> 15 | Q101: =M101+N101 -> 82.5
B102: =SUM(B96:B101) -> 29.5 | C102: =SUM(C96:C101) -> 352.5 | D102: =SUM(D96:D101) -> 141 | E102: =SUM(E96:E101) -> 0 | F102: =(C102+D102)/B102 -> 16.728814 | G102: =C102+D102 -> 493.5 | K102: - Sun 9/3 | L102: 8.5 | M102: =L102*7.25 -> 61.625 | N102: 172 | O102: 129 | P102: =(M102+N102)/L102 -> 27.485294 | Q102: =M102+N102 -> 233.625
...

Sheet Crypto Claims
A1: Fincancial Portfolio: Crypto Claims
A2: Earning Claims
A4: Crypto Staking
A5: SweatCoin
A6: Staking | B6: Date Staked | C6: Coin | D6: Price at Stake (Coin) | E6: Start Amount (Coin) | F6: Start Amount ($) | G6: Current APR | H6: Current APR Amount (Daily)
A7: Sweat Wallet
A8: Asset 1 | B8: 45283
A11: HoneyGain: JumbTask | G11: Fluid Starter: 2.1%
A12: Staking | B12: Date Staked | C12: Coin | D12: Price at Stake (Coin) | E12: Start Amount (Coin) | F12: Start Amount ($) | G12: Current APR | H12: Current APR Amount (Daily)
A13: HoneyGain: JumbTask | N13: 4
A14: Asset 1 | B14: 44951 | C14: JMPT | D14: 2.19 | E14: 23.24261 | F14: =E14*D14 -> 50.901316 | G14: 0.021 | H14: =(B23*G14)/365 -> 0.0019234878 | N14: 5
A16: Interest Earned Claims | F16: Data Claims | M16: 6
A17: New Claim Date | B17: Claim Amount (Coin) | C17: Earnings off Interest (Coin) | D17: Earnings off Interest ($) | F17: New Claim Date | G17: Claim Amount (Coin) | H17: Earnings off Interest (Coin)
A18: 11/1/2023: Start | B18: 8.9 | C18: =E14+B18 -> 32.14261 | D18: =C18*'Crypto Market Price Data'!C34 -> 23.953894 | F18: 45231 | G18: 1.28944 | H18: =G18+'Crypto Market Price Data'!C34 -> 2.034678
A21: Data Claims
A22: New Claim Date | B22: New Amount (Coin) | C22: New Amount ($)
A23: 45231 | B23: =C18+G18 -> 33.43205 | C23: =B23*'Crypto Market Price Data'!C34 -> 24.914834
A27: Axie Infinity | E27: Actual today - | F27: =E30*'Crypto Market Price Data'!$C$19 -> 9.3733477 | G27: 44704
A28: Staking | B28: Date Staked | C28: Coin | D28: Price at Purchase (Coin) | E28: Start Amount (Coin) | F28: Amount ($) | G28: Current APR | H28: Current APR Amount (Daily) | I28: Column1
A29: Ronin Staking
A30: Asset 1 | B30: 44592 | C30: AXS | D30: 52.3 | E30: 9.4185 | F30: ='Crypto Claims'!$E30*'Crypto Claims'!$D30 -> 492.58755 | G30: 0.35 | H30: =(B77*'Crypto Claims'!$G30)/365 -> 0.14091969 | I30: ='Crypto Claims'!$H30*3 -> 0.42275908
A32: Interest Earned Claims | F32: Land Claims
A33: New Claim Date | B33: Claim Amount (Coin) | C33: Earnings off Interest (Coin) | D33: Earnings off Interest ($) | F33: New Claim Date | G33: Claim Amount (Coin) | H33: Earnings off Land (Coin) | I33: Earnings off Land ($)
A34: 44616 | B34: 0.5148 | C34: =E30+B34 -> 9.9333 | D34: =C34*'Crypto Market Price Data'!$C$19 -> 9.8856798 | F34: 44783 | G34: 10.47799 | H34: ='Crypto Claims'!$G34 -> 10.47799 | I34: ='Crypto Claims'!$H34*'Crypto Market Price Data'!$C$19 -> 10.427759
A35: 44645 | B35: 0.5672 | C35: =C34+B35 -> 10.5005 | D35: =C35*'Crypto Market Price Data'!$C$19 -> 10.450161 | F35: 44805 | G35: 5.722203 | H35: =H34+'Crypto Claims'!$G35 -> 16.200193 | I35: ='Crypto Claims'!$H35*'Crypto Market Price Data'!$C$19 -> 16.122529
A36: 44675 | B36: 0.6503 | C36: =C35+B36 -> 11.1508 | D36: =C36*'Crypto Market Price Data'!$C$19 -> 11.097343 | F36: 44835 | G36: 7.638457 | H36: =H35+'Crypto Claims'!$G36 -> 23.83865 | I36: ='Crypto Claims'!$H36*'Crypto Market Price Data'!$C$19 -> 23.724368
A37: 44704 | B37: 0.6863 | C37: =C36+B37 -> 11.8371 | D37: =C37*'Crypto Market Price Data'!$C$19 -> 11.780353 | F37: 44866 | G37: 8.043623 | H37: =H36+'Crypto Claims'!$G37 -> 31.882273 | I37: ='Crypto Claims'!$H37*'Crypto Market Price Data'!$C$19 -> 31.729429
A38: 44742 | B38: 1.0035 | C38: =C37+B38 -> 12.8406 | D38: =C38*'Crypto Market Price Data'!$C$19 -> 12.779042 | F38: 44896 | G38: 7.7224013 | H38: =H37+'Crypto Claims'!$G38 -> 39.604674 | I38: ='Crypto Claims'!$H38*'Crypto Market Price Data'!$C$19 -> 39.414809
A39: 44783 | B39: 1.013614 | C39: =C38+B39 -> 13.854214 | D39: =C39*'Crypto Market Price Data'!$C$19 -> 13.787797 | F39: 44941 | G39: 11.58258 | H39: =H38+'Crypto Claims'!$G39 -> 51.187254 | I39: ='Crypto Claims'!$H39*'Crypto Market Price Data'!$C$19 -> 50.941863
A40: 44805 | B40: 0.913346 | C40: =C39+B40 -> 14.76756 | D40: =C40*'Crypto Market Price Data'!$C$19 -> 14.696764 | F40: 44958 | G40: 4.810596 | H40: =H39+'Crypto Claims'!$G40 -> 55.99785 | I40: ='Crypto Claims'!$H40*'Crypto Market Price Data'!$C$19 -> 55.729397
A41: 44835 | B41: 1.525835 | C41: =C40+B41 -> 16.293395 | D41: =C41*'Crypto Market Price Data'!$C$19 -> 16.215284 | F41: 44986 | G41: 6.301217 | H41: =H40+'Crypto Claims'!$G41 -> 62.299067 | I41: ='Crypto Claims'!$H41*'Crypto Market Price Data'!$C$19 -> 62.000406
A42: 44866 | B42: 1.691947 | C42: =C41+B42 -> 17.985342 | D42: =C42*'Crypto Market Price Data'!$C$19 -> 17.89912 | F42: 45017 | G42: 8.463442 | H42: =H41+'Crypto Claims'!$G42 -> 70.762509 | I42: ='Crypto Claims'!$H42*'Crypto Market Price Data'!$C$19 -> 70.423274
A43: 44896 | B43: 1.868694 | C43: =C42+B43 -> 19.854036 | D43: =C43*'Crypto Market Price Data'!$C$19 -> 19.758856 | F43: 45047 | G43: 7.824492 | H43: =H42+'Crypto Claims'!$G43 -> 78.587001 | I43: ='Crypto Claims'!$H43*'Crypto Market Price Data'!$C$19 -> 78.210255
A44: 44941 | B44: 3.207299 | C44: =C43+B44 -> 23.061335 | D44: =C44*'Crypto Market Price Data'!$C$19 -> 22.950779 | F44: 45078 | G44: 8.421743 | H44: =H43+'Crypto Claims'!$G44 -> 87.008744 | I44: ='Crypto Claims'!$H44*'Crypto Market Price Data'!$C$19 -> 86.591624
A45: 44958 | B45: 1.614265 | C45: =C44+B45 -> 24.6756 | D45: =C45*'Crypto Market Price Data'!$C$19 -> 24.557305 | F45: 45108 | G45: 7.333692 | H45: =H44+'Crypto Claims'!$G45 -> 94.342436 | I45: ='Crypto Claims'!$H45*'Crypto Market Price Data'!$C$19 -> 93.890159
A46: 44986 | B46: 2.31195 | C46: =C45+B46 -> 26.98755 | D46: =C46*'Crypto Market Price Data'!$C$19 -> 26.858172 | F46: 45139 | G46: 8.027721 | H46: =H45+'Crypto Claims'!$G46 -> 102.37016 | I46: ='Crypto Claims'!$H46*'Crypto Market Price Data'!$C$19 -> 101.87939
... A52: 45170 | B52: 4.354191 | C52: =C51+B52 -> 48.943143 | D52: =C52*'Crypto Market Price Data'!$C$19 -> 48.70851 | F52: 45323 | G52: 4.445978 | H52: =H51+'Crypto Claims'!$G52 -> 140.75708 | I52: ='Crypto Claims'!$H52*'Crypto Market Price Data'!$C$19 -> 140.08229
A53: 45200 | B53: 4.60166 | C53: =C52+B53 -> 53.544803 | D53: =C53*'Crypto Market Price Data'!$C$19 -> 53.288109 | F53: 45352 | G53: 0 | H53: =H52+'Crypto Claims'!$G53 -> 140.75708 | I53: ='Crypto Claims'!$H53*'Crypto Market Price Data'!$C$19 -> 140.08229 | J53: - Earnings Stopped
A54: 45231 | B54: 5.581678 | C54: =C53+B54 -> 59.126481 | D54: =C54*'Crypto Market Price Data'!$C$19 -> 58.843029 | F54: 45383 | G54: 0 | H54: =H53+'Crypto Claims'!$G54 -> 140.75708 | I54: ='Crypto Claims'!$H54*'Crypto Market Price Data'!$C$19 -> 140.08229
A55: 45261 | B55: 4.946516 | C55: =C54+B55 -> 64.072997 | D55: =C55*'Crypto Market Price Data'!$C$19 -> 63.765831 | F55: 45424 | G55: 0 | H55: =H54+'Crypto Claims'!$G55 -> 140.75708 | I55: ='Crypto Claims'!$H55*'Crypto Market Price Data'!$C$19 -> 140.08229
A56: 44927 | B56: 5.429897 | C56: =C55+B56 -> 69.502894 | D56: =C56*'Crypto Market Price Data'!$C$19 -> 69.169697
A57: 44958 | B57: 8.015257 | C57: =C56+B57 -> 77.518151 | D57: =C57*'Crypto Market Price Data'!$C$19 -> 77.146529
A58: 44986 | B58: 4.23413 | C58: =C57+B58 -> 81.752281 | D58: =C58*'Crypto Market Price Data'!$C$19 -> 81.360361
A59: 45017 | B59: 6.130493 | C59: =C58+B59 -> 87.882774 | D59: =C59*'Crypto Market Price Data'!$C$19 -> 87.461464
A60: 45058 | B60: 14.73834 | C60: =C59+B60 -> 102.62111 | D60: =C60*'Crypto Market Price Data'!$C$19 -> 102.12915
A63: Land and Interest Totals
A64: New Claim Date | B64: New Amount (Coin) | C64: New Amount ($)
A65: 44783 | B65: =C39+G34 -> 24.332204 | C65: =B65*'Crypto Market Price Data'!$C$19 -> 24.215555
A66: 44805 | B66: =B65+B40+G35 -> 30.967753 | C66: =B66*'Crypto Market Price Data'!$C$19 -> 30.819294
A67: 44835 | B67: =B66+B41+G36 -> 40.132045 | C67: =B67*'Crypto Market Price Data'!$C$19 -> 39.939652
A68: 44866 | B68: =B67+B42+G37 -> 49.867615 | C68: =B68*'Crypto Market Price Data'!$C$19 -> 49.62855
A69: 44896 | B69: =B68+B43+G38 -> 59.45871 | C69: =B69*'Crypto Market Price Data'!$C$19 -> 59.173665
A70: 44941 | B70: =B69+B44+G39 -> 74.248589 | C70: =B70*'Crypto Market Price Data'!$C$19 -> 73.892642
A71: 44958 | B71: =B70+B45+G40 -> 80.67345 | C71: =B71*'Crypto Market Price Data'!$C$19 -> 80.286702
A72: 44986 | B72: =B71+B46+G41 -> 89.286617 | C72: =B72*'Crypto Market Price Data'!$C$19 -> 88.858577
A73: 45017 | B73: =B72+B47+G42 -> 100.97668 | C73: =B73*'Crypto Market Price Data'!$C$19 -> 100.4926
A74: 45047 | B74: =B73+B48+G43 -> 111.98528 | C74: =B74*'Crypto Market Price Data'!$C$19 -> 111.44842
A75: 45078 | B75: =B74+B49+G44 -> 124.08641 | C75: =B75*'Crypto Market Price Data'!$C$19 -> 123.49154
A76: 45108 | B76: =B75+B50+G45 -> 134.90962 | C76: =B76*'Crypto Market Price Data'!$C$19 -> 134.26286
A77: 45139 | B77: =B76+B51+G46 -> 146.95911 | C77: =B77*'Crypto Market Price Data'!$C$19 -> 146.25459
... A84: 45352 | B84: =B83+B58+G53 -> 222.50936 | C84: =B84*'Crypto Market Price Data'!$C$19 -> 221.44265
A85: 45017 | B85: =B84+B59+G54 -> 228.63986 | C85: =B85*'Crypto Market Price Data'!$C$19 -> 227.54376 | E85: Coin | F85: Dollar
A86: 45058 | B86: =B85+B60+G55 -> 243.3782 | C86: =B86*'Crypto Market Price Data'!$C$19 -> 242.21144 | D86: Est. Earning Claims | E86: =B86-B65 -> 219.04599 | F86: =E86*'Crypto Market Price Data'!C19 -> 217.99589
A89: Points & Dollars | E89: 44944 | G89: 45027
A90: Video Accounts | B90: Start Date | C90: Coin | D90: Start Amount (Coin) | E90: Start Amount($) | F90: Account Status (Coin) | G90: Account Status ($)
A91: TryAtHome/HideoutTV | B91: 44660 | C91: Points | D91: 0 | E91: 0 | F91: 3815.5 | G91: ='Crypto Claims'!$F91*0.0005 -> 1.90775
A92: Loot.tv | B92: 44660 | C92: Points | D92: 0 | E92: 0 | F92: 11282.6 | G92: ='Crypto Claims'!$F92*0.0005 -> 5.6413
E94: 44944 | G94: 45027
A95: Receipt Apps | B95: Start Date | C95: Coin | D95: Start Amount (Coin) | E95: Start Amount($) | F95: Account Status (Coin) | G95: Account Status ($)
A96: Receipt Hog | B96: 44662 | C96: Points | D96: 0 | E96: 0 | F96: 1561 | G96: =(F96/6500)*40 -> 9.6061538
A97: Receipt Pal | B97: 44662 | C97: Points | D97: 0 | E97: 0 | F97: 6720 | G97: =(F97/32250)*100 -> 20.837209
A98: Fetch Rewards | B98: 44662 | C98: Points | D98: 0 | E98: 0 | F98: 17430 | G98: =(F98/52500)*50 -> 16.6
A99: Coinout | B99: 44662 | C99: Dollars | D99: 0 | E99: 0 | F99: 16.64 | G99: =Table35[[#This Row],[Account Status (Coin)]] -> 16.64
A100: Receipt Jar | B100: 44944 | C100: Points | D100: 0 | E100: 0 | F100: 275 | G100: =(Table35[[#This Row],[Account Status (Coin)]]/1000)*5 -> 1.375
A101: Pogo | B101: 44944 | C101: Points | D101: 0 | E101: 0 | F101: 1906 | G101: =(Table35[[#This Row],[Account Status (Coin)]]/1000)*1 -> 1.906
A102: Ibotta | B102: 44662 | C102: Dollars | D102: 0 | E102: 0 | F102: 1.85 | G102: =Table35[[#This Row],[Account Status (Coin)]] -> 1.85
A103: Tada | B103: 44944 | C103: Dollars | D103: 0 | E103: 0 | F103: 0 | G103: 5
E105: 44579 | G105: 45027
A106: Survey Accounts | B106: Start Date | C106: Coin | D106: Start Amount (Coin) | E106: Start Amount($) | F106: Account Status (Coin) | G106: Account Status ($)
A107: Paid Viewpoint | B107: 44652 | C107: Dollars | D107: 12.04 | E107: =Table2152[[#This Row],[Start Amount (Coin)]] -> 12.04 | F107: 32.39 | G107: =Table2152[[#This Row],[Account Status (Coin)]] -> 32.39
A108: InboxDollars | B108: 44661 | C108: Dollars | D108: 9.85 | E108: =Table2152[[#This Row],[Start Amount (Coin)]] -> 9.85 | F108: 55.53 | G108: =Table2152[[#This Row],[Account Status (Coin)]] -> 55.53
A111: App Offers | B111: Start Date | C111: Last Paid Date | D111: Coin | E111: Amount Claim ($) | F111: Amount Spent ($) | G111: Notes
A112: Merge Dragons | B112: 44652 | C112: 45103 | D112: Dollars | E112: 50
A113: Mafia City | B113: 44661 | C113: 45111 | D113: Dollars | E113: 100
A114: Chief Almighty | B114: 44797 | C114: Pending | D114: Dollars | E114: - | G114: - Not Paid
A115: Puzzles & Survival | B115: 44980 | C115: Pending | D115: Dollars | E115: - | G115: - Lv15 Reached 5/30/23
A116: Ant Legion | B116: 45061 | C116: 45097 | D116: Dollars | E116: 13 | G116: - Lv15 Reached 6/20/23
A117: The Eat Repeat: SB | B117: 45104 | D117: Dollars
A118: Puzzles & Conquest: SB | B118: 45120 | C118: 45127 | D118: Dollars | E118: 17.2 | G118: - Lv
A119: Empires & Puzzles: SB | B119: 45177 | C119: 45187 | D119: Dollars | E119: 3 | G119: - Lv3
A120: AliceDreamland | B120: 41617 | C120: 45272 | D120: Dollars | E120: 0 | F120: 16
A121: Dragonscapes | B121: 44937
B122: 41683
A124: Crypto Only | F124: 44579
A125: Faucet Accounts | B125: Start Date | C125: Coin | D125: Start Amount (Coin) | E125: Start Amount($) | F125: Account Status (Coin) | G125: Account Status ($)
A126: Cointiply | B126: 44652 | C126: BTC | D126: 0.00033702 | E126: =Table1450[[#This Row],[Start Amount (Coin)]]*'Crypto Market Price Data'!$C$5 -> 28.645015 | F126: 0.00128284 | G126: =Table1450[[#This Row],[Account Status (Coin)]]*'Crypto Market Price Data'!$C$5 -> 109.03499
F128: 44579
A129: NFT Claims | B129: Start Date | C129: Coin | D129: Start Amount (Coin) | E129: Start Amount ($) | F129: Account Status (Coin) | G129: Account Status ($)
A130: League of Kingdoms
A131: - Asset 1: Land: 139484 | B131: 40756 | C131: LOKA | D131: 3.5556 | E131: =Table4458[[#This Row],[Start Amount (Coin)]]*'Crypto Market Price Data'!$C$22 -> 0.19921671 | F131: 23.67 | G131: =Table4458[[#This Row],[Account Status (Coin)]]*'Crypto Market Price Data'!$C$22 -> 1.3262064
...

Sheet General Crypto Earnings
A1: Fincancial Portfolio: Crypto Earnings
A2: General Crypto Earnings
A5: GPU & CPU Miners:
A6: Miner Website: | B6: Wallet | C6: Coin | D6: Mh (Average) | E6: Profit/Day (Coin) | F6: Profit/Week (Coin) | G6: Profit/Month (Coin) | H6: Profit/Year (Coin) | I6: Profit/Day ($) | J6: Profit/Week ($) | K6: Profit/Month ($) | L6: Profit/Year ($)
A7: Unmineable: SHIBA | B7: Atomic: 0x0C203Fcf60F1e7B6224D1f44641e51715f4C434D | C7: SHIBA | D7: 23.1 | E7: 15037.213 | F7: =Table27[[#This Row],[Profit/Day (Coin)]]*7 -> 105260.49 | G7: =Table27[[#This Row],[Profit/Day (Coin)]]*30 -> 451116.4 | H7: =Table27[[#This Row],[Profit/Month (Coin)]]*12 -> 5413396.8 | I7: =Table27[[#This Row],[Profit/Day (Coin)]]*'Crypto Market Price Data'!$C$10 -> 0.11879398 | J7: =Table27[[#This Row],[Profit/Week (Coin)]]*'Crypto Market Price Data'!$C$10 -> 0.83155789 | K7: =Table27[[#This Row],[Profit/Month (Coin)]]*'Crypto Market Price Data'!$C$10 -> 3.5638195 | L7: =Table27[[#This Row],[Profit/Year (Coin)]]*'Crypto Market Price Data'!$C$10 -> 42.765834
H9: Avg. Total: | I9: =I7 -> 0.11879398 | J9: =J7 -> 0.83155789 | K9: =K7 -> 3.5638195 | L9: =L7 -> 42.765834
A11: Exchange Miners:
A12: Miner Website: | B12: Wallet | C12: Coin | D12: Miner Level | E12: Profit/Day (Coin) | F12: Profit/Week (Coin) | G12: Profit/Month (Coin) | H12: Profit/Year (Coin) | I12: Profit/Day ($) | J12: Profit/Week ($) | K12: Profit/Month ($) | L12: Profit/Year ($)
A13: StormGain | B13: In-App | C13: BTC | D13: 1 | E13: 1.08e-05 | F13: =Table28[[#This Row],[Profit/Day (Coin)]]*7 -> 7.56e-05 | G13: =Table28[[#This Row],[Profit/Day (Coin)]]*30 -> 0.000324 | H13: =Table28[[#This Row],[Profit/Month (Coin)]]*12 -> 0.003888 | I13: =Table28[[#This Row],[Profit/Day (Coin)]]*'Crypto Market Price Data'!$C$5 -> 0.917946 | J13: =Table28[[#This Row],[Profit/Week (Coin)]]*'Crypto Market Price Data'!$C$5 -> 6.425622 | K13: =Table28[[#This Row],[Profit/Month (Coin)]]*'Crypto Market Price Data'!$C$5 -> 27.53838 | L13: =Table28[[#This Row],[Profit/Year (Coin)]]*'Crypto Market Price Data'!$C$5 -> 330.46056 | M13: x5 + 15% of referals
H15: Avg. Total: | I15: =I13 -> 0.917946 | J15: =J13 -> 6.425622 | K15: =K13 -> 27.53838 | L15: =L13 -> 330.46056 | M15: with 15% every month
A17: Data Miners:
A18: Miner Website: | B18: Wallet | C18: Coin | D18: Referrals | E18: Profit/Day (Coin) | F18: Profit/Week (Coin) | G18: Profit/Month (Coin) | H18: Profit/Year (Coin) | I18: Profit/Day ($) | J18: Profit/Week ($) | K18: Profit/Month ($) | L18: Profit/Year ($)
A19: HoneyGain
A20: - Asset 1: HoneyGain | B20: In-App | C20: BTC | D20: 3 | E20: 120 | F20: =Table29[[#This Row],[Profit/Day (Coin)]]*7 -> 840 | G20: =Table29[[#This Row],[Profit/Day (Coin)]]*30 -> 3600 | H20: =Table29[[#This Row],[Profit/Month (Coin)]]*12 -> 43200 | I20: 0.12 | J20: 0.84 | K20: 3.6 | L20: 43.8
A21: - Asset 2: JumpTask | B21: In-App | C21: JMPT | D21: 3 | E21: 0.09 | F21: =Table29[[#This Row],[Profit/Day (Coin)]]*7 -> 0.63 | G21: =Table29[[#This Row],[Profit/Day (Coin)]]*30 -> 2.7 | H21: =Table29[[#This Row],[Profit/Month (Coin)]]*12 -> 32.4 | I21: =Table29[[#This Row],[Profit/Day (Coin)]]*'Crypto Market Price Data'!$C$34 -> 0.06707142 | J21: =Table29[[#This Row],[Profit/Week (Coin)]]*'Crypto Market Price Data'!$C$34 -> 0.46949994 | K21: =Table29[[#This Row],[Profit/Month (Coin)]]*'Crypto Market Price Data'!$C$34 -> 2.0121426 | L21: =Table29[[#This Row],[Profit/Year (Coin)]]*'Crypto Market Price Data'!$C$34 -> 24.145711
H22: Avg. Total: | I22: =SUM(I20:I21) -> 0.18707142 | J22: =SUM(J20:J21) -> 1.3094999 | K22: =SUM(K20:K21) -> 5.6121426 | L22: =SUM(L20:L21) -> 67.945711
A24: Other Miners
A25: Other Miners | B25: Wallet | C25: Coin | D25: Profit/Day ($) | E25: Profit/Week($) | F25: Profit/Month ($) | G25: Profit/Year ($)
A26: Kryptex | B26: In-App | C26: Dollars | D26: 0.4 | E26: =Table30[[#This Row],[Profit/Day ($)]]*7 -> 2.8 | F26: =Table30[[#This Row],[Profit/Day ($)]]*30 -> 12 | G26: =Table30[[#This Row],[Profit/Month ($)]]*12 -> 144
C27: Avg. Total | D27: {=Table30[Profit/Day ($)]} -> 0.4 | E27: {=Table30[Profit/Week($)]} -> 2.8 | F27: {=Table30[Profit/Month ($)]} -> 12 | G27: {=Table30[Profit/Year ($)]} -> 144
A29: NFT Accounts:
A30: NFT Website | B30: Coin | C30: Profit/Day (Coin) | D30: Profit/Week (Coin) | E30: Profit/Month (Coin) | F30: Profit/Year (Coin) | G30: Profit/Day ($) | H30: Profit/Week($) | I30: Profit/Month ($) | J30: Profit/Year ($)
A31: Axie Infinity (Land) | B31: AXS | C31: 0.208 | D31: =Table31[[#This Row],[Profit/Day (Coin)]]*7 -> 1.456 | E31: =Table31[[#This Row],[Profit/Day (Coin)]]*30 -> 6.24 | F31: =Table31[[#This Row],[Profit/Month (Coin)]]*12 -> 74.88 | G31: =Table31[[#This Row],[Profit/Day (Coin)]]*'Crypto Market Price Data'!$C$19 -> 0.20700285 | H31: =Table31[[#This Row],[Profit/Week (Coin)]]*'Crypto Market Price Data'!$C$19 -> 1.4490199 | I31: =Table31[[#This Row],[Profit/Month (Coin)]]*'Crypto Market Price Data'!$C$19 -> 6.2100854 | J31: =Table31[[#This Row],[Profit/Year (Coin)]]*'Crypto Market Price Data'!$C$19 -> 74.521025
A32: TownStar | B32: TOWN | C32: 19 | D32: =Table31[[#This Row],[Profit/Day (Coin)]]*7 -> 133 | E32: =Table31[[#This Row],[Profit/Day (Coin)]]*30 -> 570 | F32: =Table31[[#This Row],[Profit/Month (Coin)]]*12 -> 6840 | G32: =Table31[[#This Row],[Profit/Day (Coin)]]*'Crypto Market Price Data'!$C$24 -> 0.0222091 | H32: =Table31[[#This Row],[Profit/Week (Coin)]]*'Crypto Market Price Data'!$C$24 -> 0.1554637 | I32: =Table31[[#This Row],[Profit/Month (Coin)]]*'Crypto Market Price Data'!$C$24 -> 0.666273 | J32: =Table31[[#This Row],[Profit/Year (Coin)]]*'Crypto Market Price Data'!$C$24 -> 7.995276
A33: League of Kingdoms
A34: Asset 1 | B34: LOKA | C34: 0.22 | D34: =Table31[[#This Row],[Profit/Day (Coin)]]*7 -> 1.54 | E34: =Table31[[#This Row],[Profit/Day (Coin)]]*30 -> 6.6 | F34: =Table31[[#This Row],[Profit/Month (Coin)]]*12 -> 79.2 | G34: =Table31[[#This Row],[Profit/Day (Coin)]]*'Crypto Market Price Data'!$C$22 -> 0.01232638 | H34: =Table31[[#This Row],[Profit/Week (Coin)]]*'Crypto Market Price Data'!$C$22 -> 0.08628466 | I34: =Table31[[#This Row],[Profit/Month (Coin)]]*'Crypto Market Price Data'!$C$22 -> 0.3697914 | J34: =Table31[[#This Row],[Profit/Year (Coin)]]*'Crypto Market Price Data'!$C$22 -> 4.4374968
A35: Asset 2 | B35: DAI | C35: 0.2 | D35: =Table31[[#This Row],[Profit/Day (Coin)]]*7 -> 1.4 | E35: =Table31[[#This Row],[Profit/Day (Coin)]]*30 -> 6 | F35: =Table31[[#This Row],[Profit/Month (Coin)]]*12 -> 72 | G35: =Table31[[#This Row],[Profit/Day (Coin)]]*'Crypto Market Price Data'!$C$11 -> 0.1998938 | H35: =Table31[[#This Row],[Profit/Week (Coin)]]*'Crypto Market Price Data'!$C$11 -> 1.3992566 | I35: =Table31[[#This Row],[Profit/Month (Coin)]]*'Crypto Market Price Data'!$C$11 -> 5.996814 | J35: =Table31[[#This Row],[Profit/Year (Coin)]]*'Crypto Market Price Data'!$C$11 -> 71.961768
A36: Voxie Tactics | B36: VOXEL | C36: 1 | D36: =Table31[[#This Row],[Profit/Day (Coin)]]*7 -> 7 | E36: =Table31[[#This Row],[Profit/Day (Coin)]]*30 -> 30 | F36: =Table31[[#This Row],[Profit/Month (Coin)]]*12 -> 360 | G36: =Table31[[#This Row],[Profit/Day (Coin)]]*'Crypto Market Price Data'!$C$26 -> 0.02621318 | H36: =Table31[[#This Row],[Profit/Week (Coin)]]*'Crypto Market Price Data'!$C$26 -> 0.18349226 | I36: =Table31[[#This Row],[Profit/Month (Coin)]]*'Crypto Market Price Data'!$C$26 -> 0.7863954 | J36: =Table31[[#This Row],[Profit/Year (Coin)]]*'Crypto Market Price Data'!$C$26 -> 9.4367448
A37: Blankos | B37: MOOLA
F38: Avg. Total: | G38: =SUM(Table31[Profit/Day ($)]) -> 0.46764531 | H38: =SUM(Table31[Profit/Week($)]) -> 3.2735172 | I38: =SUM(Table31[Profit/Month ($)]) -> 14.029359 | J38: =SUM(Table31[Profit/Year ($)]) -> 168.35231
A40: Crypto Games: | G40: Total Badges = 10 - 5%
A41: Passive Games | B41: Coin | C41: Base Rate per Rarity/Second | D41: Number of Items | E41: Pre Total/Sec | F41: Badges (5%) | G41: Bonus (x30) | H41: Profit/Sec ($) | I41: Profit/Min ($) | J41: Profit/Hour ($) | K41: Profit/Day ($) | L41: Profit/Week($) | M41: Profit/Month ($) | N41: Profit/Year ($)
A42: Atlas
A43: Asset 1: Common Land | B43: $ | C43: 1.11e-09 | D43: 60 | E43: =Table32[[#This Row],[Base Rate per Rarity/Second]]*Table32[[#This Row],[Number of Items]] -> 6.66e-08 | F43: =(Table32[[#This Row],[Pre Total/Sec]]*0.05)+Table32[[#This Row],[Pre Total/Sec]] -> 6.993e-08 | G43: =Table32[[#This Row],[Badges (5%)]]*30 -> 2.0979e-06 | H43: =Table32[[#This Row],[Bonus (x30)]] -> 2.0979e-06 | I43: =Table32[[#This Row],[Profit/Sec ($)]]*60 -> 0.000125874 | J43: =Table32[[#This Row],[Profit/Min ($)]]*60 -> 0.00755244 | K43: =Table32[[#This Row],[Profit/Hour ($)]]*24 -> 0.18125856 | L43: =Table32[[#This Row],[Profit/Day ($)]]*7 -> 1.2688099 | M43: =Table32[[#This Row],[Profit/Day ($)]]*30 -> 5.4377568 | N43: =Table32[[#This Row],[Profit/Month ($)]]*12 -> 65.253082
A44: Asset 2: Rare Land | B44: $ | C44: 1.66e-09 | D44: 37 | E44: =Table32[[#This Row],[Base Rate per Rarity/Second]]*Table32[[#This Row],[Number of Items]] -> 6.142e-08 | F44: =(Table32[[#This Row],[Pre Total/Sec]]*0.05)+Table32[[#This Row],[Pre Total/Sec]] -> 6.4491e-08 | G44: =Table32[[#This Row],[Badges (5%)]]*30 -> 1.93473e-06 | H44: =Table32[[#This Row],[Bonus (x30)]] -> 1.93473e-06 | I44: =Table32[[#This Row],[Profit/Sec ($)]]*60 -> 0.0001160838 | J44: =Table32[[#This Row],[Profit/Min ($)]]*60 -> 0.006965028 | K44: =Table32[[#This Row],[Profit/Hour ($)]]*24 -> 0.16716067 | L44: =Table32[[#This Row],[Profit/Day ($)]]*7 -> 1.1701247 | M44: =Table32[[#This Row],[Profit/Day ($)]]*30 -> 5.0148202 | N44: =Table32[[#This Row],[Profit/Month ($)]]*12 -> 60.177842
A45: Asset 3: Epic Land | B45: $ | C45: 2.22e-09 | D45: 17 | E45: =Table32[[#This Row],[Base Rate per Rarity/Second]]*Table32[[#This Row],[Number of Items]] -> 3.774e-08 | F45: =(Table32[[#This Row],[Pre Total/Sec]]*0.05)+Table32[[#This Row],[Pre Total/Sec]] -> 3.9627e-08 | G45: =Table32[[#This Row],[Badges (5%)]]*30 -> 1.18881e-06 | H45: =Table32[[#This Row],[Bonus (x30)]] -> 1.18881e-06 | I45: =Table32[[#This Row],[Profit/Sec ($)]]*60 -> 7.13286e-05 | J45: =Table32[[#This Row],[Profit/Min ($)]]*60 -> 0.004279716 | K45: =Table32[[#This Row],[Profit/Hour ($)]]*24 -> 0.10271318 | L45: =Table32[[#This Row],[Profit/Day ($)]]*7 -> 0.71899229 | M45: =Table32[[#This Row],[Profit/Day ($)]]*30 -> 3.0813955 | N45: =Table32[[#This Row],[Profit/Month ($)]]*12 -> 36.976746
A46: Asset 4: Legendary Land | B46: $ | C46: 4.44e-09 | D46: 4 | E46: =Table32[[#This Row],[Base Rate per Rarity/Second]]*Table32[[#This Row],[Number of Items]] -> 1.776e-08 | F46: =(Table32[[#This Row],[Pre Total/Sec]]*0.05)+Table32[[#This Row],[Pre Total/Sec]] -> 1.8648e-08 | G46: =Table32[[#This Row],[Badges (5%)]]*30 -> 5.5944e-07 | H46: =Table32[[#This Row],[Bonus (x30)]] -> 5.5944e-07 | I46: =Table32[[#This Row],[Profit/Sec ($)]]*60 -> 3.35664e-05 | J46: =Table32[[#This Row],[Profit/Min ($)]]*60 -> 0.002013984 | K46: =Table32[[#This Row],[Profit/Hour ($)]]*24 -> 0.048335616 | L46: =Table32[[#This Row],[Profit/Day ($)]]*7 -> 0.33834931 | M46: =Table32[[#This Row],[Profit/Day ($)]]*30 -> 1.4500685 | N46: =Table32[[#This Row],[Profit/Month ($)]]*12 -> 17.400822
B47: Avg. Total: | C47: =SUM(C43:C46) -> 9.43e-09 | D47: =SUM(D43:D46) -> 118 | E47: =SUM(E43:E46) -> 1.8352e-07 | F47: =SUM(F43:F46) -> 1.92696e-07 | G47: =SUM(G43:G46) -> 5.78088e-06 | H47: =SUM(H43:H46) -> 5.78088e-06 | I47: =SUM(I43:I46) -> 0.0003468528 | J47: =SUM(J43:J46) -> 0.020811168 | ... N47: =SUM(N43:N46) -> 179.80849
A49: Video Accounts:
A50: VIdeo Website | B50: Coin | C50: Points/Hour | D50: Points/Day | E50: Points/Week | F50: Points/Month | G50: Points/Year | H50: Profit/Day ($) | I50: Profit/Week($) | J50: Profit/Month ($) | K50: Profit/Year ($)
A51: TryAtHome/HideoutTV/LootTV
A52: Asset 1: HidehoutTV | B52: Points | C52: 22.7 | D52: =Table33[[#This Row],[Points/Hour]]*24 -> 544.8 | E52: =Table33[[#This Row],[Points/Day]]*7 -> 3813.6 | F52: =Table33[[#This Row],[Points/Day]]*30 -> 16344 | G52: =Table33[[#This Row],[Points/Month]]*12 -> 196128 | H52: =Table33[[#This Row],[Points/Day]]/1000 -> 0.5448 | I52: =Table33[[#This Row],[Points/Week]]/1000 -> 3.8136 | J52: =Table33[[#This Row],[Points/Month]]/1000 -> 16.344 | K52: =Table33[[#This Row],[Points/Year]]/1000 -> 196.128
A53: Asset 2: LootTV | B53: Points | C53: 22.7 | D53: =Table33[[#This Row],[Points/Hour]]*24 -> 544.8 | E53: =Table33[[#This Row],[Points/Day]]*7 -> 3813.6 | F53: =Table33[[#This Row],[Points/Day]]*30 -> 16344 | G53: =Table33[[#This Row],[Points/Month]]*12 -> 196128 | H53: =Table33[[#This Row],[Points/Day]]/1000 -> 0.5448 | I53: =Table33[[#This Row],[Points/Week]]/1000 -> 3.8136 | J53: =Table33[[#This Row],[Points/Month]]/1000 -> 16.344 | K53: =Table33[[#This Row],[Points/Year]]/1000 -> 196.128
G54: Avg. Total: | H54: =SUM(H52:H53) -> 1.0896 | I54: =SUM(I52:I53) -> 7.6272 | J54: =SUM(J52:J53) -> 32.688 | K54: =SUM(K52:K53) -> 392.256
A56: Staking: Interest Earned | F56: 45261
A57: Staking | B57: Date Staked | C57: Coin | D57: Start Amount (Coin) | E57: Start Amount ($) | F57: Todays Amount (Coin) | G57: Current APR | H57: Current APR Amount (Daily) | I57: Profit/Day ($) | J57: Profit/Week($) | K57: Profit/Month ($) | L57: Profit/Year ($)
A58: HoneyGain: JumbTask
A59: Asset 1 | B59: 44945 | C59: JMPT | D59: 22.90476 | E59: =D59*'Crypto Market Price Data'!$C$34 -> 17.069498 | F59: =23.24261+3.37268 -> 26.61529 | G59: 0.14 | H59: =(Table14[[#This Row],[Todays Amount (Coin)]]*G59)/365 -> 0.010208604 | I59: =Table14[[#This Row],[Current APR Amount (Daily)]]*'Crypto Market Price Data'!$C$34 -> 0.0076078399 | J59: =Table14[[#This Row],[Profit/Day ($)]]*7 -> 0.053254879 | K59: =Table14[[#This Row],[Profit/Day ($)]]*30 -> 0.2282352 | L59: =Table14[[#This Row],[Profit/Day ($)]]*365 -> 2.7768616
A60: Ronin Staking | J60: .
A61: Asset 1: Interest | B61: 44592 | C61: AXS | D61: 74.248 | E61: =D61*'Crypto Market Price Data'!$C$19 -> 73.892055 | F61: ='Crypto Claims'!C60 -> 102.62111 | G61: 0.35 | H61: =(Table14[[#This Row],[Todays Amount (Coin)]]*G61)/365 -> 0.098403808 | I61: =Table14[[#This Row],[Current APR Amount (Daily)]]*'Crypto Market Price Data'!$C$19 -> 0.09793206 | J61: =Table14[[#This Row],[Profit/Day ($)]]*7 -> 0.68552442 | K61: =Table14[[#This Row],[Profit/Day ($)]]*30 -> 2.9379618 | L61: =Table14[[#This Row],[Profit/Day ($)]]*365 -> 35.745202
H62: Avg. Total: | I62: =SUM(Table14[Profit/Day ($)]) -> 0.1055399 | J62: =SUM(Table14[Profit/Week($)]) -> 0.7387793 | K62: =SUM(Table14[Profit/Month ($)]) -> 3.166197 | L62: =SUM(Table14[Profit/Year ($)]) -> 38.522064
A65: Total Passive Earnings ($/Day) | B65: Total Passive Earnings ($/Week) | C65: Total Passive Earnings ($/Month) | D65: Total Passive Earnings ($/Year)
A66: =I9+I15+I22+D27+G38+K47+H54+I62 -> 3.7860646 | B66: =J9+J15+J22+E27+H38+L47+I54+I62 -> 25.869213 | C66: =K9+K15+K22+F27+I38+M47+J54+J62 -> 111.15452 | D66: =L9+L15+L22+G27+J38+N47+K54+K62 -> 1328.7551

Sheet Crypto Market Price Data
A1: Fincancial Portfolio: Crypto Market Data
A2: Coin Prices
A4: Main Crypto Coins | B4: Ticker | C4: PRICE
A5: Bitcoin (BTC) | B5: BTC | C5: {=_xll.ART(B5:B13,C4)} -> 84995
A6: Ethereum (ETH) | B6: ETH | C6: 2740.59
A7: Binance Token (BNB) | B7: BNB | C7: 814.72
A8: Cardano (ADA) | B8: ADA | C8: 0.376492
A9: Solana (SOL) | B9: SOL | C9: 123.88
A10: Shiba Inu (SHIB) | B10: SHIB | C10: 7.9e-06
A11: Dai Token (DAI) | B11: DAI | C11: 0.999469
A12: Cronos (CRO) | B12: CRO | C12: 0.09995
A13: Basic Attention Token (BAT) | B13: BAT | C13: 0.249377
A16: Gaming Crypto Coins | B16: Ticker | C16: PRICE
A17: Decentraland (MANA) | B17: MANA | C17: {=_xll.ART(B17:B26,C16)} -> 0.147749
A18: Theta Network (THETA) | B18: THETA | C18: 0.30617
A19: Axie Infinity (AXS) | B19: AXS | C19: 0.995206
A20: The Sandbox (SAND) | B20: SAND | C20: 0.139297
A21: Gala Games (GALA) | B21: GALA | C21: 0.00671289
A22: League of Kingdoms (LOKA) | B22: LOKA | C22: 0.056029
A23: Phantasma (SOUL) | B23: SOUL | C23: 0.01253937
A24: Town Star (TOWN) | B24: TOWN | C24: 0.0011689
A25: Materium (MTRM) | B25: MTRM | C25: 0.00795619
A26: Voxie Tactics (VOXEL) | B26: VOXEL | C26: 0.02621318
A29: Miner Crypto Coins | B29: Ticker | C29: PRICE
A30: Geo Coin (XYO) | B30: XYO | C30: {=_xll.ART(B30:B35,C29)} -> 0.00474776
A31: Sperax (SPX) | B31: SPX | C31: 0.602333
A32: Pi Network (PI) | B32: PI | C32: 0.225658
A33: Nodle Network (NODL) | B33: NODL | C33: 0.000105
A34: JumpToken (JMPT) | B34: JMPT | C34: 0.745238
A35: SweatCoin | B35: SWEAT | C35: 0.00156458
